{
"meta":{"test_sets":[],"test_metrics":[],"learn_metrics":[{"best_value":"Min","name":"Logloss"}],"launch_mode":"Train","parameters":"","iteration_count":1000,"learn_sets":["learn"],"name":"experiment"},
"iterations":[
{"learn":[0.6813316783],"iteration":0,"passed_time":0.1738559357,"remaining_time":173.6820797},
{"learn":[0.6713015537],"iteration":1,"passed_time":0.1961769035,"remaining_time":97.89227485},
{"learn":[0.6608993671],"iteration":2,"passed_time":0.2181007159,"remaining_time":72.48213793},
{"learn":[0.6515256875],"iteration":3,"passed_time":0.2368032463,"remaining_time":58.96400832},
{"learn":[0.6410298891],"iteration":4,"passed_time":0.2590283605,"remaining_time":51.54664375},
{"learn":[0.6315052532],"iteration":5,"passed_time":0.2825369344,"remaining_time":46.80695213},
{"learn":[0.6224008466],"iteration":6,"passed_time":0.3035153291,"remaining_time":43.0558174},
{"learn":[0.6139491493],"iteration":7,"passed_time":0.3286738399,"remaining_time":40.75555615},
{"learn":[0.6054802035],"iteration":8,"passed_time":0.3522579756,"remaining_time":38.78751709},
{"learn":[0.5981278105],"iteration":9,"passed_time":0.3697269719,"remaining_time":36.60297022},
{"learn":[0.5912943525],"iteration":10,"passed_time":0.3936595772,"remaining_time":35.39357472},
{"learn":[0.5866793415],"iteration":11,"passed_time":0.4040691663,"remaining_time":33.26836136},
{"learn":[0.580359837],"iteration":12,"passed_time":0.4245922228,"remaining_time":32.236348},
{"learn":[0.5744202409],"iteration":13,"passed_time":0.4417273882,"remaining_time":31.11022891},
{"learn":[0.5681538186],"iteration":14,"passed_time":0.4634759324,"remaining_time":30.43491956},
{"learn":[0.5608505797],"iteration":15,"passed_time":0.4867185169,"remaining_time":29.93318879},
{"learn":[0.5539512306],"iteration":16,"passed_time":0.5093142102,"remaining_time":29.45034521},
{"learn":[0.5482386991],"iteration":17,"passed_time":0.5324553583,"remaining_time":29.04839788},
{"learn":[0.5420431999],"iteration":18,"passed_time":0.5556610273,"remaining_time":28.6896562},
{"learn":[0.5362970573],"iteration":19,"passed_time":0.5780407547,"remaining_time":28.32399698},
{"learn":[0.5318659826],"iteration":20,"passed_time":0.593313257,"remaining_time":27.65969898},
{"learn":[0.5263074351],"iteration":21,"passed_time":0.6161124656,"remaining_time":27.38899961},
{"learn":[0.5218547121],"iteration":22,"passed_time":0.6350927064,"remaining_time":26.97763366},
{"learn":[0.51741878],"iteration":23,"passed_time":0.659368106,"remaining_time":26.81430298},
{"learn":[0.5132595838],"iteration":24,"passed_time":0.6805363194,"remaining_time":26.54091646},
{"learn":[0.5095824086],"iteration":25,"passed_time":0.7000114179,"remaining_time":26.22350466},
{"learn":[0.5058802782],"iteration":26,"passed_time":0.7222144299,"remaining_time":26.02646816},
{"learn":[0.5019612046],"iteration":27,"passed_time":0.7435014286,"remaining_time":25.81012102},
{"learn":[0.4983967792],"iteration":28,"passed_time":0.7647548716,"remaining_time":25.60610277},
{"learn":[0.4948602622],"iteration":29,"passed_time":0.7854690316,"remaining_time":25.39683202},
{"learn":[0.4912026358],"iteration":30,"passed_time":0.807685106,"remaining_time":25.24667315},
{"learn":[0.4878513033],"iteration":31,"passed_time":0.8288332238,"remaining_time":25.07220502},
{"learn":[0.4846510933],"iteration":32,"passed_time":0.8524837049,"remaining_time":24.98035584},
{"learn":[0.4815439898],"iteration":33,"passed_time":0.8752122084,"remaining_time":24.86632333},
{"learn":[0.4788064855],"iteration":34,"passed_time":0.895767842,"remaining_time":24.69759907},
{"learn":[0.4763137282],"iteration":35,"passed_time":0.9162091593,"remaining_time":24.53404527},
{"learn":[0.473945458],"iteration":36,"passed_time":0.9376784717,"remaining_time":24.40498293},
{"learn":[0.4714887051],"iteration":37,"passed_time":0.9603551562,"remaining_time":24.31214895},
{"learn":[0.4689874784],"iteration":38,"passed_time":0.9817194695,"remaining_time":24.19057462},
{"learn":[0.4665804292],"iteration":39,"passed_time":1.021332928,"remaining_time":24.51199028},
{"learn":[0.4645079352],"iteration":40,"passed_time":1.054167147,"remaining_time":24.65722669},
{"learn":[0.4624483209],"iteration":41,"passed_time":1.073710144,"remaining_time":24.49081709},
{"learn":[0.4603781077],"iteration":42,"passed_time":1.096195727,"remaining_time":24.39672816},
{"learn":[0.4586176998],"iteration":43,"passed_time":1.115772243,"remaining_time":24.24268783},
{"learn":[0.4568034002],"iteration":44,"passed_time":1.140403047,"remaining_time":24.20188688},
{"learn":[0.4549629043],"iteration":45,"passed_time":1.160347683,"remaining_time":24.06460195},
{"learn":[0.4533317664],"iteration":46,"passed_time":1.181234002,"remaining_time":23.95140433},
{"learn":[0.4516968827],"iteration":47,"passed_time":1.202601901,"remaining_time":23.85160436},
{"learn":[0.4501678222],"iteration":48,"passed_time":1.223564659,"remaining_time":23.74714266},
{"learn":[0.4487820388],"iteration":49,"passed_time":1.240621463,"remaining_time":23.57180779},
{"learn":[0.4472917047],"iteration":50,"passed_time":1.264102572,"remaining_time":23.52222238},
{"learn":[0.4458244962],"iteration":51,"passed_time":1.285264654,"remaining_time":23.43136331},
{"learn":[0.4445859415],"iteration":52,"passed_time":1.306594753,"remaining_time":23.34613643},
{"learn":[0.4434136112],"iteration":53,"passed_time":1.326252244,"remaining_time":23.2339745},
{"learn":[0.4420630325],"iteration":54,"passed_time":1.349173747,"remaining_time":23.18125802},
{"learn":[0.4405426215],"iteration":55,"passed_time":1.36959637,"remaining_time":23.08748167},
{"learn":[0.4392636119],"iteration":56,"passed_time":1.392349845,"remaining_time":23.03484041},
{"learn":[0.4378339947],"iteration":57,"passed_time":1.415197859,"remaining_time":22.98476523},
{"learn":[0.436622092],"iteration":58,"passed_time":1.435916459,"remaining_time":22.90165065},
{"learn":[0.4356663435],"iteration":59,"passed_time":1.459662835,"remaining_time":22.86805108},
{"learn":[0.4348626384],"iteration":60,"passed_time":1.475385715,"remaining_time":22.71126535},
{"learn":[0.4337847036],"iteration":61,"passed_time":1.495053794,"remaining_time":22.61871707},
{"learn":[0.4327019194],"iteration":62,"passed_time":1.515618949,"remaining_time":22.54182469},
{"learn":[0.4316181096],"iteration":63,"passed_time":1.538755758,"remaining_time":22.50430296},
{"learn":[0.4309598105],"iteration":64,"passed_time":1.560087458,"remaining_time":22.44125805},
{"learn":[0.4306386976],"iteration":65,"passed_time":1.567876521,"remaining_time":22.18782834},
{"learn":[0.4296022059],"iteration":66,"passed_time":1.58959088,"remaining_time":22.13564614},
{"learn":[0.4286372267],"iteration":67,"passed_time":1.614112472,"remaining_time":22.12283565},
{"learn":[0.4283164908],"iteration":68,"passed_time":1.621370618,"remaining_time":21.87675428},
{"learn":[0.4274003606],"iteration":69,"passed_time":1.643326036,"remaining_time":21.83276019},
{"learn":[0.4265458661],"iteration":70,"passed_time":1.666220991,"remaining_time":21.80168028},
{"learn":[0.4257359258],"iteration":71,"passed_time":1.688256565,"remaining_time":21.75975128},
{"learn":[0.4250098592],"iteration":72,"passed_time":1.709807197,"remaining_time":21.7122092},
{"learn":[0.4247391724],"iteration":73,"passed_time":1.721079126,"remaining_time":21.5367469},
{"learn":[0.4243792759],"iteration":74,"passed_time":1.73278431,"remaining_time":21.37100649},
{"learn":[0.4239735903],"iteration":75,"passed_time":1.748317437,"remaining_time":21.25585937},
{"learn":[0.4231544578],"iteration":76,"passed_time":1.768316098,"remaining_time":21.19682803},
{"learn":[0.4223020622],"iteration":77,"passed_time":1.790144004,"remaining_time":21.16042015},
{"learn":[0.4216166184],"iteration":78,"passed_time":1.812489612,"remaining_time":21.13041687},
{"learn":[0.4214414412],"iteration":79,"passed_time":1.82028723,"remaining_time":20.93330314},
{"learn":[0.4207706565],"iteration":80,"passed_time":1.839183827,"remaining_time":20.86678934},
{"learn":[0.4202157788],"iteration":81,"passed_time":1.859984015,"remaining_time":20.82274787},
{"learn":[0.4199220044],"iteration":82,"passed_time":1.872960386,"remaining_time":20.69282739},
{"learn":[0.4195149727],"iteration":83,"passed_time":1.895000078,"remaining_time":20.66452466},
{"learn":[0.4189676692],"iteration":84,"passed_time":1.915793213,"remaining_time":20.62295047},
{"learn":[0.4182515456],"iteration":85,"passed_time":1.937350203,"remaining_time":20.58997773},
{"learn":[0.4176412281],"iteration":86,"passed_time":1.960443171,"remaining_time":20.57338638},
{"learn":[0.4172064284],"iteration":87,"passed_time":1.981916626,"remaining_time":20.53986322},
{"learn":[0.4166591354],"iteration":88,"passed_time":2.003254386,"remaining_time":20.50522186},
{"learn":[0.4165574786],"iteration":89,"passed_time":2.012557712,"remaining_time":20.34919465},
{"learn":[0.416137818],"iteration":90,"passed_time":2.036580483,"remaining_time":20.34342482},
{"learn":[0.4158048633],"iteration":91,"passed_time":2.058594797,"remaining_time":20.31743561},
{"learn":[0.4152047904],"iteration":92,"passed_time":2.087671179,"remaining_time":20.36040602},
{"learn":[0.41459105],"iteration":93,"passed_time":2.112357668,"remaining_time":20.35953242},
{"learn":[0.4142092041],"iteration":94,"passed_time":2.134212653,"remaining_time":20.33118369},
{"learn":[0.4139738792],"iteration":95,"passed_time":2.151790765,"remaining_time":20.26269637},
{"learn":[0.4135760509],"iteration":96,"passed_time":2.170674538,"remaining_time":20.20741348},
{"learn":[0.413281562],"iteration":97,"passed_time":2.192101114,"remaining_time":20.1762776},
{"learn":[0.4127348984],"iteration":98,"passed_time":2.214427267,"remaining_time":20.15352493},
{"learn":[0.4122871344],"iteration":99,"passed_time":2.236163682,"remaining_time":20.12547314},
{"learn":[0.4119475308],"iteration":100,"passed_time":2.257190653,"remaining_time":20.09123165},
{"learn":[0.4116200587],"iteration":101,"passed_time":2.277154363,"remaining_time":20.04788841},
{"learn":[0.4112746856],"iteration":102,"passed_time":2.297045672,"remaining_time":20.00436862},
{"learn":[0.4109716043],"iteration":103,"passed_time":2.31932552,"remaining_time":19.9818814},
{"learn":[0.4106294615],"iteration":104,"passed_time":2.344978188,"remaining_time":19.98814741},
{"learn":[0.4103569184],"iteration":105,"passed_time":2.361530139,"remaining_time":19.91705608},
{"learn":[0.4098970799],"iteration":106,"passed_time":2.383534154,"remaining_time":19.89248598},
{"learn":[0.4095820205],"iteration":107,"passed_time":2.404410334,"remaining_time":19.85864831},
{"learn":[0.4092485982],"iteration":108,"passed_time":2.426671378,"remaining_time":19.83636878},
{"learn":[0.4091779865],"iteration":109,"passed_time":2.437936604,"remaining_time":19.72512343},
{"learn":[0.4087345231],"iteration":110,"passed_time":2.468502533,"remaining_time":19.77025902},
{"learn":[0.4084699684],"iteration":111,"passed_time":2.490252574,"remaining_time":19.74414541},
{"learn":[0.4082793639],"iteration":112,"passed_time":2.508914608,"remaining_time":19.69386953},
{"learn":[0.4079236692],"iteration":113,"passed_time":2.531315599,"remaining_time":19.6732072},
{"learn":[0.4076887027],"iteration":114,"passed_time":2.552340904,"remaining_time":19.64192783},
{"learn":[0.4071654832],"iteration":115,"passed_time":2.576734281,"remaining_time":19.63649228},
{"learn":[0.406852941],"iteration":116,"passed_time":2.59856185,"remaining_time":19.61136849},
{"learn":[0.4064156425],"iteration":117,"passed_time":2.620771969,"remaining_time":19.58915997},
{"learn":[0.4062080505],"iteration":118,"passed_time":2.642688685,"remaining_time":19.56477926},
{"learn":[0.4058880097],"iteration":119,"passed_time":2.666122847,"remaining_time":19.55156755},
{"learn":[0.4055567952],"iteration":120,"passed_time":2.688084339,"remaining_time":19.52748871},
{"learn":[0.405194599],"iteration":121,"passed_time":2.711869546,"remaining_time":19.51656935},
{"learn":[0.4048658541],"iteration":122,"passed_time":2.73702087,"remaining_time":19.51518133},
{"learn":[0.4048203272],"iteration":123,"passed_time":2.750122172,"remaining_time":19.42828244},
{"learn":[0.4045163426],"iteration":124,"passed_time":2.771541826,"remaining_time":19.40079278},
{"learn":[0.4042615404],"iteration":125,"passed_time":2.792467862,"remaining_time":19.36997549},
{"learn":[0.4039783104],"iteration":126,"passed_time":2.815017692,"remaining_time":19.35047594},
{"learn":[0.4037787149],"iteration":127,"passed_time":2.836434099,"remaining_time":19.3232073},
{"learn":[0.4036403635],"iteration":128,"passed_time":2.859773937,"remaining_time":19.30901628},
{"learn":[0.4033004309],"iteration":129,"passed_time":2.88264589,"remaining_time":19.29155326},
{"learn":[0.4030494076],"iteration":130,"passed_time":2.905237997,"remaining_time":19.27215129},
{"learn":[0.4027464897],"iteration":131,"passed_time":2.93009781,"remaining_time":19.26761287},
{"learn":[0.4023744309],"iteration":132,"passed_time":2.95714512,"remaining_time":19.27702871},
{"learn":[0.4021448354],"iteration":133,"passed_time":2.986655894,"remaining_time":19.30182093},
{"learn":[0.4019426115],"iteration":134,"passed_time":3.015127319,"remaining_time":19.31914912},
{"learn":[0.4017643912],"iteration":135,"passed_time":3.041192332,"remaining_time":19.32051599},
{"learn":[0.4017263655],"iteration":136,"passed_time":3.055243035,"remaining_time":19.24580102},
{"learn":[0.4014202363],"iteration":137,"passed_time":3.078387552,"remaining_time":19.22876862},
{"learn":[0.4009805265],"iteration":138,"passed_time":3.098711044,"remaining_time":19.19417416},
{"learn":[0.4008997285],"iteration":139,"passed_time":3.110516294,"remaining_time":19.10745724},
{"learn":[0.4007720657],"iteration":140,"passed_time":3.128951645,"remaining_time":19.06219477},
{"learn":[0.4004317348],"iteration":141,"passed_time":3.152714902,"remaining_time":19.04950272},
{"learn":[0.4003604372],"iteration":142,"passed_time":3.176555215,"remaining_time":19.03711762},
{"learn":[0.400316908],"iteration":143,"passed_time":3.204666062,"remaining_time":19.04995937},
{"learn":[0.4003144645],"iteration":144,"passed_time":3.216891152,"remaining_time":18.96856507},
{"learn":[0.4001436502],"iteration":145,"passed_time":3.24559244,"remaining_time":18.98449277},
{"learn":[0.3999591538],"iteration":146,"passed_time":3.288738719,"remaining_time":19.08363352},
{"learn":[0.3996704502],"iteration":147,"passed_time":3.314204779,"remaining_time":19.07907075},
{"learn":[0.3995267034],"iteration":148,"passed_time":3.334634771,"remaining_time":19.04546436},
{"learn":[0.399307177],"iteration":149,"passed_time":3.357231685,"remaining_time":19.02431288},
{"learn":[0.3989921001],"iteration":150,"passed_time":3.387142326,"remaining_time":19.04426381},
{"learn":[0.3988841447],"iteration":151,"passed_time":3.408089287,"remaining_time":19.01355076},
{"learn":[0.3987751082],"iteration":152,"passed_time":3.431734055,"remaining_time":18.99790029},
{"learn":[0.3985654419],"iteration":153,"passed_time":3.454153714,"remaining_time":18.97541586},
{"learn":[0.3985200167],"iteration":154,"passed_time":3.4649071,"remaining_time":18.88933225},
{"learn":[0.3982174542],"iteration":155,"passed_time":3.486656818,"remaining_time":18.8637074},
{"learn":[0.3980624614],"iteration":156,"passed_time":3.509756988,"remaining_time":18.84538306},
{"learn":[0.3976237365],"iteration":157,"passed_time":3.580062149,"remaining_time":19.07855905},
{"learn":[0.3974059777],"iteration":158,"passed_time":3.619404797,"remaining_time":19.14414739},
{"learn":[0.3972135276],"iteration":159,"passed_time":3.64660611,"remaining_time":19.14468208},
{"learn":[0.3970596963],"iteration":160,"passed_time":3.672797428,"remaining_time":19.13960896},
{"learn":[0.3968396809],"iteration":161,"passed_time":3.70370377,"remaining_time":19.15866518},
{"learn":[0.3966719907],"iteration":162,"passed_time":3.731901114,"remaining_time":19.16319774},
{"learn":[0.3966471727],"iteration":163,"passed_time":3.741410312,"remaining_time":19.0720672},
{"learn":[0.3965690994],"iteration":164,"passed_time":3.764160605,"remaining_time":19.04893397},
{"learn":[0.3964464643],"iteration":165,"passed_time":3.791676712,"remaining_time":19.04974926},
{"learn":[0.3962926817],"iteration":166,"passed_time":3.817154153,"remaining_time":19.04005634},
{"learn":[0.3961609645],"iteration":167,"passed_time":3.838795221,"remaining_time":19.01117633},
{"learn":[0.3960234559],"iteration":168,"passed_time":3.860439502,"remaining_time":18.98239779},
{"learn":[0.3960117716],"iteration":169,"passed_time":3.871912445,"remaining_time":18.90404312},
{"learn":[0.3958033934],"iteration":170,"passed_time":3.893017707,"remaining_time":18.87316771},
{"learn":[0.395691632],"iteration":171,"passed_time":3.914382106,"remaining_time":18.84365339},
{"learn":[0.3955947027],"iteration":172,"passed_time":3.936278505,"remaining_time":18.81677644},
{"learn":[0.3953483054],"iteration":173,"passed_time":3.959679139,"remaining_time":18.79709752},
{"learn":[0.3952310705],"iteration":174,"passed_time":3.983539006,"remaining_time":18.77954103},
{"learn":[0.3950167639],"iteration":175,"passed_time":4.004281138,"remaining_time":18.74731624},
{"learn":[0.3948455105],"iteration":176,"passed_time":4.026674427,"remaining_time":18.72289861},
{"learn":[0.3945059269],"iteration":177,"passed_time":4.048714089,"remaining_time":18.69687068},
{"learn":[0.3944044176],"iteration":178,"passed_time":4.066213869,"remaining_time":18.65006473},
{"learn":[0.3942977172],"iteration":179,"passed_time":4.089338988,"remaining_time":18.62921095},
{"learn":[0.3942059183],"iteration":180,"passed_time":4.110154342,"remaining_time":18.5978807},
{"learn":[0.3941746474],"iteration":181,"passed_time":4.12428357,"remaining_time":18.53661516},
{"learn":[0.3941320345],"iteration":182,"passed_time":4.147091208,"remaining_time":18.51460938},
{"learn":[0.3939742402],"iteration":183,"passed_time":4.169631731,"remaining_time":18.49141028},
{"learn":[0.3939468747],"iteration":184,"passed_time":4.187306778,"remaining_time":18.44678391},
{"learn":[0.3938657017],"iteration":185,"passed_time":4.208060925,"remaining_time":18.41592254},
{"learn":[0.3938041029],"iteration":186,"passed_time":4.230599255,"remaining_time":18.39292617},
{"learn":[0.3936673922],"iteration":187,"passed_time":4.252483664,"remaining_time":18.36711029},
{"learn":[0.3935126114],"iteration":188,"passed_time":4.275371605,"remaining_time":18.34564218},
{"learn":[0.3934614542],"iteration":189,"passed_time":4.297553417,"remaining_time":18.32114878},
{"learn":[0.3933272261],"iteration":190,"passed_time":4.320916941,"remaining_time":18.30168485},
{"learn":[0.3931750319],"iteration":191,"passed_time":4.34325238,"remaining_time":18.27785377},
{"learn":[0.3930793259],"iteration":192,"passed_time":4.365802086,"remaining_time":18.25493411},
{"learn":[0.3930159586],"iteration":193,"passed_time":4.387687903,"remaining_time":18.22926005},
{"learn":[0.3929761645],"iteration":194,"passed_time":4.408166715,"remaining_time":18.19781644},
{"learn":[0.3928368128],"iteration":195,"passed_time":4.431078576,"remaining_time":18.17646518},
{"learn":[0.3928163172],"iteration":196,"passed_time":4.438963251,"remaining_time":18.09384513},
{"learn":[0.392739558],"iteration":197,"passed_time":4.462175224,"remaining_time":18.07406328},
{"learn":[0.3925854851],"iteration":198,"passed_time":4.484194586,"remaining_time":18.04944655},
{"learn":[0.3925572842],"iteration":199,"passed_time":4.495268476,"remaining_time":17.98107391},
{"learn":[0.3925186226],"iteration":200,"passed_time":4.517690747,"remaining_time":17.95838262},
{"learn":[0.3924592926],"iteration":201,"passed_time":4.543605415,"remaining_time":17.9494907},
{"learn":[0.3923683774],"iteration":202,"passed_time":4.565700474,"remaining_time":17.92543487},
{"learn":[0.3922897625],"iteration":203,"passed_time":4.586726634,"remaining_time":17.89722745},
{"learn":[0.3922081268],"iteration":204,"passed_time":4.608342955,"remaining_time":17.87137878},
{"learn":[0.3920164496],"iteration":205,"passed_time":4.629134724,"remaining_time":17.84239306},
{"learn":[0.3919984482],"iteration":206,"passed_time":4.644913923,"remaining_time":17.79428377},
{"learn":[0.3918104003],"iteration":207,"passed_time":4.668377884,"remaining_time":17.77574656},
{"learn":[0.3917342388],"iteration":208,"passed_time":4.690534519,"remaining_time":17.75221437},
{"learn":[0.3915847683],"iteration":209,"passed_time":4.712234734,"remaining_time":17.72697828},
{"learn":[0.3914592271],"iteration":210,"passed_time":4.748655125,"remaining_time":17.7568194},
{"learn":[0.3912200453],"iteration":211,"passed_time":4.770680235,"remaining_time":17.73252842},
{"learn":[0.3910295845],"iteration":212,"passed_time":4.794025054,"remaining_time":17.71313482},
{"learn":[0.3908761371],"iteration":213,"passed_time":4.814930899,"remaining_time":17.6847462},
{"learn":[0.390767511],"iteration":214,"passed_time":4.837072876,"remaining_time":17.6609405},
{"learn":[0.3907463954],"iteration":215,"passed_time":4.854200219,"remaining_time":17.61894894},
{"learn":[0.3906948319],"iteration":216,"passed_time":4.877191784,"remaining_time":17.59834639},
{"learn":[0.3903908958],"iteration":217,"passed_time":4.897741232,"remaining_time":17.56896167},
{"learn":[0.3903688302],"iteration":218,"passed_time":4.90972283,"remaining_time":17.50910288},
{"learn":[0.390223666],"iteration":219,"passed_time":4.932111751,"remaining_time":17.48657803},
{"learn":[0.3899951339],"iteration":220,"passed_time":4.963975357,"remaining_time":17.4974516},
{"learn":[0.3899609487],"iteration":221,"passed_time":4.992367693,"remaining_time":17.49577507},
{"learn":[0.3898120203],"iteration":222,"passed_time":5.016338876,"remaining_time":17.47845429},
{"learn":[0.3897758307],"iteration":223,"passed_time":5.037376713,"remaining_time":17.45091219},
{"learn":[0.3897655743],"iteration":224,"passed_time":5.058511654,"remaining_time":17.42376237},
{"learn":[0.3896347133],"iteration":225,"passed_time":5.082922873,"remaining_time":17.4078863},
{"learn":[0.3893897758],"iteration":226,"passed_time":5.105721128,"remaining_time":17.38644243},
{"learn":[0.3893765791],"iteration":227,"passed_time":5.12644144,"remaining_time":17.35795084},
{"learn":[0.3893159735],"iteration":228,"passed_time":5.149859644,"remaining_time":17.33861042},
{"learn":[0.3891872284],"iteration":229,"passed_time":5.173093994,"remaining_time":17.31861902},
{"learn":[0.3891664968],"iteration":230,"passed_time":5.186139327,"remaining_time":17.26468027},
{"learn":[0.3890194705],"iteration":231,"passed_time":5.20972885,"remaining_time":17.24599895},
{"learn":[0.3889995016],"iteration":232,"passed_time":5.225397661,"remaining_time":17.20120174},
{"learn":[0.3889120941],"iteration":233,"passed_time":5.245173405,"remaining_time":17.17009756},
{"learn":[0.3887830392],"iteration":234,"passed_time":5.268965587,"remaining_time":17.15216457},
{"learn":[0.3887548867],"iteration":235,"passed_time":5.279137913,"remaining_time":17.09009053},
{"learn":[0.3886835968],"iteration":236,"passed_time":5.300726829,"remaining_time":17.06520916},
{"learn":[0.3886230058],"iteration":237,"passed_time":5.320932154,"remaining_time":17.03592563},
{"learn":[0.3885397389],"iteration":238,"passed_time":5.345498781,"remaining_time":17.02060491},
{"learn":[0.3885351684],"iteration":239,"passed_time":5.357302538,"remaining_time":16.96479137},
{"learn":[0.3884918688],"iteration":240,"passed_time":5.378698068,"remaining_time":16.93955118},
{"learn":[0.3884568416],"iteration":241,"passed_time":5.396431627,"remaining_time":16.90287262},
{"learn":[0.3884173737],"iteration":242,"passed_time":5.417313097,"remaining_time":16.87615644},
{"learn":[0.3884147785],"iteration":243,"passed_time":5.433767698,"remaining_time":16.83577205},
{"learn":[0.3883660341],"iteration":244,"passed_time":5.456067717,"remaining_time":16.81359643},
{"learn":[0.3882207461],"iteration":245,"passed_time":5.476466629,"remaining_time":16.78559284},
{"learn":[0.3881942152],"iteration":246,"passed_time":5.500263162,"remaining_time":16.76800875},
{"learn":[0.3880839842],"iteration":247,"passed_time":5.521716077,"remaining_time":16.74326811},
{"learn":[0.3880272732],"iteration":248,"passed_time":5.545037691,"remaining_time":16.72418998},
{"learn":[0.3879657519],"iteration":249,"passed_time":5.566193761,"remaining_time":16.69858128},
{"learn":[0.387923653],"iteration":250,"passed_time":5.587859704,"remaining_time":16.67452955},
{"learn":[0.3879213542],"iteration":251,"passed_time":5.595622483,"remaining_time":16.60922864},
{"learn":[0.387765193],"iteration":252,"passed_time":5.617142431,"remaining_time":16.58500156},
{"learn":[0.3877102757],"iteration":253,"passed_time":5.638512372,"remaining_time":16.56035523},
{"learn":[0.3876437987],"iteration":254,"passed_time":5.658832367,"remaining_time":16.53266711},
{"learn":[0.3876347188],"iteration":255,"passed_time":5.667347861,"remaining_time":16.47072972},
{"learn":[0.3875221872],"iteration":256,"passed_time":5.688180061,"remaining_time":16.44481629},
{"learn":[0.3874412997],"iteration":257,"passed_time":5.712965092,"remaining_time":16.43031046},
{"learn":[0.3874412978],"iteration":258,"passed_time":5.724031772,"remaining_time":16.376477},
{"learn":[0.3874328494],"iteration":259,"passed_time":5.744216872,"remaining_time":16.34892494},
{"learn":[0.387307129],"iteration":260,"passed_time":5.765353703,"remaining_time":16.32412409},
{"learn":[0.3872788948],"iteration":261,"passed_time":5.776417865,"remaining_time":16.27097857},
{"learn":[0.3872788937],"iteration":262,"passed_time":5.783182217,"remaining_time":16.20610378},
{"learn":[0.3872395047],"iteration":263,"passed_time":5.803389473,"remaining_time":16.17914641},
{"learn":[0.3871677156],"iteration":264,"passed_time":5.825541054,"remaining_time":16.15763274},
{"learn":[0.3871508474],"iteration":265,"passed_time":5.8342031,"remaining_time":16.09889126},
{"learn":[0.387132102],"iteration":266,"passed_time":5.844689913,"remaining_time":16.04553448},
{"learn":[0.3870504989],"iteration":267,"passed_time":5.867169832,"remaining_time":16.02525492},
{"learn":[0.3870147885],"iteration":268,"passed_time":5.8878217,"remaining_time":15.99999131},
{"learn":[0.3870147884],"iteration":269,"passed_time":5.893442375,"remaining_time":15.93412198},
{"learn":[0.386920245],"iteration":270,"passed_time":5.915230281,"remaining_time":15.91218773},
{"learn":[0.3869196565],"iteration":271,"passed_time":5.925605537,"remaining_time":15.85970894},
{"learn":[0.3868826114],"iteration":272,"passed_time":5.947739555,"remaining_time":15.83885222},
{"learn":[0.3867849066],"iteration":273,"passed_time":5.970297078,"remaining_time":15.81910832},
{"learn":[0.3867757584],"iteration":274,"passed_time":5.981984951,"remaining_time":15.7706876},
{"learn":[0.3867592601],"iteration":275,"passed_time":5.991785711,"remaining_time":15.71758281},
{"learn":[0.3866566629],"iteration":276,"passed_time":6.012839122,"remaining_time":15.69416132},
{"learn":[0.3866513587],"iteration":277,"passed_time":6.020381293,"remaining_time":15.63566652},
{"learn":[0.3865685084],"iteration":278,"passed_time":6.042717011,"remaining_time":15.6157669},
{"learn":[0.3865238272],"iteration":279,"passed_time":6.065302309,"remaining_time":15.59649165},
{"learn":[0.3865238261],"iteration":280,"passed_time":6.070250248,"remaining_time":15.5320638},
{"learn":[0.3864636819],"iteration":281,"passed_time":6.092667322,"remaining_time":15.51253595},
{"learn":[0.3864317214],"iteration":282,"passed_time":6.11292254,"remaining_time":15.48751046},
{"learn":[0.3863371689],"iteration":283,"passed_time":6.135832758,"remaining_time":15.46921216},
{"learn":[0.3861745323],"iteration":284,"passed_time":6.158774831,"remaining_time":15.45096142},
{"learn":[0.386098036],"iteration":285,"passed_time":6.183858811,"remaining_time":15.43802514},
{"learn":[0.3859388702],"iteration":286,"passed_time":6.209438432,"remaining_time":15.42623555},
{"learn":[0.3859237611],"iteration":287,"passed_time":6.232026451,"remaining_time":15.40695428},
{"learn":[0.3858352796],"iteration":288,"passed_time":6.253012551,"remaining_time":15.38370908},
{"learn":[0.385685042],"iteration":289,"passed_time":6.276041605,"remaining_time":15.36548117},
{"learn":[0.3855397068],"iteration":290,"passed_time":6.298137176,"remaining_time":15.3449459},
{"learn":[0.3855397058],"iteration":291,"passed_time":6.305767374,"remaining_time":15.28932637},
{"learn":[0.3855397048],"iteration":292,"passed_time":6.312826217,"remaining_time":15.23265575},
{"learn":[0.3854471236],"iteration":293,"passed_time":6.333751549,"remaining_time":15.20962107},
{"learn":[0.3852885687],"iteration":294,"passed_time":6.35894894,"remaining_time":15.19681018},
{"learn":[0.3851266022],"iteration":295,"passed_time":6.383920042,"remaining_time":15.1833774},
{"learn":[0.3851044228],"iteration":296,"passed_time":6.405598674,"remaining_time":15.16207363},
{"learn":[0.3850350911],"iteration":297,"passed_time":6.42460955,"remaining_time":15.1344829},
{"learn":[0.3850026315],"iteration":298,"passed_time":6.444628507,"remaining_time":15.10931299},
{"learn":[0.3850026163],"iteration":299,"passed_time":6.452676811,"remaining_time":15.05624589},
{"learn":[0.3848423312],"iteration":300,"passed_time":6.474843696,"remaining_time":15.03626493},
{"learn":[0.3845904838],"iteration":301,"passed_time":6.497399865,"remaining_time":15.01716922},
{"learn":[0.3845487885],"iteration":302,"passed_time":6.517785003,"remaining_time":14.99305659},
{"learn":[0.3845225951],"iteration":303,"passed_time":6.539207741,"remaining_time":14.97134404},
{"learn":[0.3844475751],"iteration":304,"passed_time":6.56010574,"remaining_time":14.94843767},
{"learn":[0.3843946606],"iteration":305,"passed_time":6.582164267,"remaining_time":14.92817647},
{"learn":[0.3843944259],"iteration":306,"passed_time":6.590008132,"remaining_time":14.8758164},
{"learn":[0.38435063],"iteration":307,"passed_time":6.61029627,"remaining_time":14.85170461},
{"learn":[0.3842063655],"iteration":308,"passed_time":6.633085624,"remaining_time":14.83321089},
{"learn":[0.3841973417],"iteration":309,"passed_time":6.653965593,"remaining_time":14.81043955},
{"learn":[0.3841535163],"iteration":310,"passed_time":6.68963007,"remaining_time":14.82043446},
{"learn":[0.384107403],"iteration":311,"passed_time":6.712118339,"remaining_time":14.80108147},
{"learn":[0.384018854],"iteration":312,"passed_time":6.734440074,"remaining_time":14.78134291},
{"learn":[0.3838840216],"iteration":313,"passed_time":6.759257765,"remaining_time":14.76704085},
{"learn":[0.3838554541],"iteration":314,"passed_time":6.784405366,"remaining_time":14.75338945},
{"learn":[0.3837991935],"iteration":315,"passed_time":6.806430418,"remaining_time":14.73290635},
{"learn":[0.3836436978],"iteration":316,"passed_time":6.828329633,"remaining_time":14.71214239},
{"learn":[0.3835643505],"iteration":317,"passed_time":6.84919008,"remaining_time":14.68914351},
{"learn":[0.3835068209],"iteration":318,"passed_time":6.871190983,"remaining_time":14.66859266},
{"learn":[0.3835068183],"iteration":319,"passed_time":6.878198698,"remaining_time":14.61617223},
{"learn":[0.3835068158],"iteration":320,"passed_time":6.886910338,"remaining_time":14.567639},
{"learn":[0.383460708],"iteration":321,"passed_time":6.908959381,"remaining_time":14.54743621},
{"learn":[0.3833463649],"iteration":322,"passed_time":6.930108262,"remaining_time":14.52533527},
{"learn":[0.3832214722],"iteration":323,"passed_time":6.951928157,"remaining_time":14.50464023},
{"learn":[0.383118275],"iteration":324,"passed_time":6.973413288,"remaining_time":14.48324298},
{"learn":[0.3830501674],"iteration":325,"passed_time":6.997479258,"remaining_time":14.46718104},
{"learn":[0.3830440841],"iteration":326,"passed_time":7.020433753,"remaining_time":14.44878262},
{"learn":[0.3830253738],"iteration":327,"passed_time":7.034442938,"remaining_time":14.41202943},
{"learn":[0.382948206],"iteration":328,"passed_time":7.055592949,"remaining_time":14.38997832},
{"learn":[0.3827693673],"iteration":329,"passed_time":7.077324011,"remaining_time":14.36911239},
{"learn":[0.3827684116],"iteration":330,"passed_time":7.084843491,"remaining_time":14.31951751},
{"learn":[0.3827605397],"iteration":331,"passed_time":7.097042397,"remaining_time":14.27959133},
{"learn":[0.3826077559],"iteration":332,"passed_time":7.120468343,"remaining_time":14.26231947},
{"learn":[0.3825280264],"iteration":333,"passed_time":7.140894441,"remaining_time":14.23902904},
{"learn":[0.382478405],"iteration":334,"passed_time":7.165262277,"remaining_time":14.22358034},
{"learn":[0.3824541165],"iteration":335,"passed_time":7.187122559,"remaining_time":14.20312315},
{"learn":[0.3824469123],"iteration":336,"passed_time":7.208917251,"remaining_time":14.1825286},
{"learn":[0.3823564368],"iteration":337,"passed_time":7.23092078,"remaining_time":14.16233597},
{"learn":[0.3822360805],"iteration":338,"passed_time":7.252892235,"remaining_time":14.14207011},
{"learn":[0.3822173412],"iteration":339,"passed_time":7.272146018,"remaining_time":14.11651874},
{"learn":[0.381943136],"iteration":340,"passed_time":7.293512401,"remaining_time":14.09508702},
{"learn":[0.3818922927],"iteration":341,"passed_time":7.316099042,"remaining_time":14.07600342},
{"learn":[0.3816868621],"iteration":342,"passed_time":7.337730608,"remaining_time":14.05507},
{"learn":[0.3816503098],"iteration":343,"passed_time":7.361578474,"remaining_time":14.03835895},
{"learn":[0.381646199],"iteration":344,"passed_time":7.387242415,"remaining_time":14.02505444},
{"learn":[0.3816442117],"iteration":345,"passed_time":7.401880416,"remaining_time":13.99083755},
{"learn":[0.3816058042],"iteration":346,"passed_time":7.427440285,"remaining_time":13.97728676},
{"learn":[0.381605803],"iteration":347,"passed_time":7.432722671,"remaining_time":13.92567581},
{"learn":[0.3816029858],"iteration":348,"passed_time":7.45355732,"remaining_time":13.90334044},
{"learn":[0.3816017203],"iteration":349,"passed_time":7.460747694,"remaining_time":13.85567429},
{"learn":[0.3815845592],"iteration":350,"passed_time":7.474532194,"remaining_time":13.82043132},
{"learn":[0.3814902373],"iteration":351,"passed_time":7.49692225,"remaining_time":13.80115232},
{"learn":[0.3814009592],"iteration":352,"passed_time":7.522936906,"remaining_time":13.78849909},
{"learn":[0.3813436344],"iteration":353,"passed_time":7.551447728,"remaining_time":13.78032552},
{"learn":[0.3813390059],"iteration":354,"passed_time":7.566033852,"remaining_time":13.74673756},
{"learn":[0.381315589],"iteration":355,"passed_time":7.590983459,"remaining_time":13.73200379},
{"learn":[0.3813018771],"iteration":356,"passed_time":7.608871929,"remaining_time":13.70449482},
{"learn":[0.3811312812],"iteration":357,"passed_time":7.632697248,"remaining_time":13.68768613},
{"learn":[0.3810547536],"iteration":358,"passed_time":7.654712077,"remaining_time":13.66760569},
{"learn":[0.3810370333],"iteration":359,"passed_time":7.676995766,"remaining_time":13.64799247},
{"learn":[0.3809982286],"iteration":360,"passed_time":7.699832147,"remaining_time":13.62934278},
{"learn":[0.3809417914],"iteration":361,"passed_time":7.711835429,"remaining_time":13.59157736},
{"learn":[0.3808107312],"iteration":362,"passed_time":7.732583831,"remaining_time":13.5693},
{"learn":[0.3808009223],"iteration":363,"passed_time":7.749934412,"remaining_time":13.54109419},
{"learn":[0.3806949076],"iteration":364,"passed_time":7.771677747,"remaining_time":13.52059005},
{"learn":[0.380622079],"iteration":365,"passed_time":7.793152334,"remaining_time":13.49961361},
{"learn":[0.3804874376],"iteration":366,"passed_time":7.814618717,"remaining_time":13.47862029},
{"learn":[0.3804258323],"iteration":367,"passed_time":7.83696889,"remaining_time":13.45914222},
{"learn":[0.3803250623],"iteration":368,"passed_time":7.857734251,"remaining_time":13.43693852},
{"learn":[0.3803004515],"iteration":369,"passed_time":7.880253288,"remaining_time":13.41772857},
{"learn":[0.3802219643],"iteration":370,"passed_time":7.900999521,"remaining_time":13.39549514},
{"learn":[0.3801435493],"iteration":371,"passed_time":7.923607778,"remaining_time":13.37641313},
{"learn":[0.3800618676],"iteration":372,"passed_time":7.946894821,"remaining_time":13.35845322},
{"learn":[0.3799901539],"iteration":373,"passed_time":7.970145803,"remaining_time":13.34040447},
{"learn":[0.3799427893],"iteration":374,"passed_time":7.992702246,"remaining_time":13.32117041},
{"learn":[0.3798376143],"iteration":375,"passed_time":8.013535245,"remaining_time":13.29905849},
{"learn":[0.3796982666],"iteration":376,"passed_time":8.036600255,"remaining_time":13.2806418},
{"learn":[0.3796242995],"iteration":377,"passed_time":8.059898527,"remaining_time":13.26258435},
{"learn":[0.3794637758],"iteration":378,"passed_time":8.083294742,"remaining_time":13.24465972},
{"learn":[0.3793742196],"iteration":379,"passed_time":8.105497368,"remaining_time":13.22475886},
{"learn":[0.3791759161],"iteration":380,"passed_time":8.127521224,"remaining_time":13.20455548},
{"learn":[0.3791664885],"iteration":381,"passed_time":8.149080577,"remaining_time":13.18359109},
{"learn":[0.3791409439],"iteration":382,"passed_time":8.171416804,"remaining_time":13.16387511},
{"learn":[0.3791280104],"iteration":383,"passed_time":8.17932468,"remaining_time":13.12100001},
{"learn":[0.3790745456],"iteration":384,"passed_time":8.201453254,"remaining_time":13.10102273},
{"learn":[0.3789766253],"iteration":385,"passed_time":8.223718726,"remaining_time":13.08125207},
{"learn":[0.3788703295],"iteration":386,"passed_time":8.245480842,"remaining_time":13.06067121},
{"learn":[0.378780345],"iteration":387,"passed_time":8.276643,"remaining_time":13.05491112},
{"learn":[0.378645012],"iteration":388,"passed_time":8.298597322,"remaining_time":13.03455775},
{"learn":[0.3785040933],"iteration":389,"passed_time":8.319210958,"remaining_time":13.01209919},
{"learn":[0.3784565002],"iteration":390,"passed_time":8.347021216,"remaining_time":13.00085913},
{"learn":[0.3784036647],"iteration":391,"passed_time":8.381156287,"remaining_time":12.99934444},
{"learn":[0.3783577371],"iteration":392,"passed_time":8.407010527,"remaining_time":12.98487377},
{"learn":[0.3783122982],"iteration":393,"passed_time":8.449551337,"remaining_time":12.99601043},
{"learn":[0.378121066],"iteration":394,"passed_time":8.477887416,"remaining_time":12.9851187},
{"learn":[0.3780253116],"iteration":395,"passed_time":8.516530965,"remaining_time":12.98986036},
{"learn":[0.3779401734],"iteration":396,"passed_time":8.544726054,"remaining_time":12.97851338},
{"learn":[0.3779343933],"iteration":397,"passed_time":8.57930228,"remaining_time":12.9767336},
{"learn":[0.3778781874],"iteration":398,"passed_time":8.612198642,"remaining_time":12.97225911},
{"learn":[0.3777613424],"iteration":399,"passed_time":8.640385125,"remaining_time":12.96057769},
{"learn":[0.3776982352],"iteration":400,"passed_time":8.664378535,"remaining_time":12.94255048},
{"learn":[0.3775030381],"iteration":401,"passed_time":8.69093359,"remaining_time":12.9283042},
{"learn":[0.3773188753],"iteration":402,"passed_time":8.742492636,"remaining_time":12.95103748},
{"learn":[0.3771846329],"iteration":403,"passed_time":8.783664398,"remaining_time":12.95807916},
{"learn":[0.3771588215],"iteration":404,"passed_time":8.822523953,"remaining_time":12.96148581},
{"learn":[0.3769943904],"iteration":405,"passed_time":8.857592004,"remaining_time":12.95913707},
{"learn":[0.3769588198],"iteration":406,"passed_time":8.892763185,"remaining_time":12.95677781},
{"learn":[0.3768138622],"iteration":407,"passed_time":8.932365102,"remaining_time":12.96068662},
{"learn":[0.3768087682],"iteration":408,"passed_time":8.964318418,"remaining_time":12.95333053},
{"learn":[0.3768057383],"iteration":409,"passed_time":8.988009607,"remaining_time":12.93396504},
{"learn":[0.3766334194],"iteration":410,"passed_time":9.022890083,"remaining_time":12.93061377},
{"learn":[0.3766254985],"iteration":411,"passed_time":9.032797841,"remaining_time":12.89146876},
{"learn":[0.3765572013],"iteration":412,"passed_time":9.057614995,"remaining_time":12.87365618},
{"learn":[0.3764383493],"iteration":413,"passed_time":9.080052662,"remaining_time":12.85244169},
{"learn":[0.3763793864],"iteration":414,"passed_time":9.102355007,"remaining_time":12.83103055},
{"learn":[0.3761580983],"iteration":415,"passed_time":9.126435799,"remaining_time":12.81211179},
{"learn":[0.3761481358],"iteration":416,"passed_time":9.13700735,"remaining_time":12.77428126},
{"learn":[0.3760570445],"iteration":417,"passed_time":9.157800394,"remaining_time":12.75081299},
{"learn":[0.3759541779],"iteration":418,"passed_time":9.181423319,"remaining_time":12.7312815},
{"learn":[0.3758978906],"iteration":419,"passed_time":9.205931443,"remaining_time":12.71295294},
{"learn":[0.3758402833],"iteration":420,"passed_time":9.227141242,"remaining_time":12.69005886},
{"learn":[0.3756872201],"iteration":421,"passed_time":9.249389919,"remaining_time":12.66859567},
{"learn":[0.3754999435],"iteration":422,"passed_time":9.272766322,"remaining_time":12.64866706},
{"learn":[0.3754287682],"iteration":423,"passed_time":9.290282211,"remaining_time":12.62076074},
{"learn":[0.3753092556],"iteration":424,"passed_time":9.31162273,"remaining_time":12.59807781},
{"learn":[0.3751207319],"iteration":425,"passed_time":9.335506818,"remaining_time":12.57882844},
{"learn":[0.3750521137],"iteration":426,"passed_time":9.356227174,"remaining_time":12.55531187},
{"learn":[0.3749178472],"iteration":427,"passed_time":9.377720915,"remaining_time":12.53284197},
{"learn":[0.3749178187],"iteration":428,"passed_time":9.382766579,"remaining_time":12.48848419},
{"learn":[0.374893785],"iteration":429,"passed_time":9.405122182,"remaining_time":12.46725499},
{"learn":[0.3746884572],"iteration":430,"passed_time":9.425981223,"remaining_time":12.44404482},
{"learn":[0.3746188376],"iteration":431,"passed_time":9.449143743,"remaining_time":12.42387418},
{"learn":[0.3745987847],"iteration":432,"passed_time":9.471164739,"remaining_time":12.40219494},
{"learn":[0.3743413041],"iteration":433,"passed_time":9.492016095,"remaining_time":12.37898873},
{"learn":[0.3743083042],"iteration":434,"passed_time":9.515351039,"remaining_time":12.35901917},
{"learn":[0.3742812207],"iteration":435,"passed_time":9.536937877,"remaining_time":12.33677285},
{"learn":[0.3741952623],"iteration":436,"passed_time":9.559371556,"remaining_time":12.31562056},
{"learn":[0.3740827931],"iteration":437,"passed_time":9.580323458,"remaining_time":12.29256115},
{"learn":[0.3740779818],"iteration":438,"passed_time":9.594349212,"remaining_time":12.26066038},
{"learn":[0.3740009108],"iteration":439,"passed_time":9.616658654,"remaining_time":12.23938374},
{"learn":[0.3738186195],"iteration":440,"passed_time":9.639405185,"remaining_time":12.21865646},
{"learn":[0.3738178411],"iteration":441,"passed_time":9.650438798,"remaining_time":12.18313314},
{"learn":[0.3737029596],"iteration":442,"passed_time":9.671227944,"remaining_time":12.15998638},
{"learn":[0.3736767571],"iteration":443,"passed_time":9.694884503,"remaining_time":12.14044095},
{"learn":[0.3736559274],"iteration":444,"passed_time":9.732484242,"remaining_time":12.13826686},
{"learn":[0.3735824997],"iteration":445,"passed_time":9.755435916,"remaining_time":12.11773878},
{"learn":[0.3734724158],"iteration":446,"passed_time":9.777337823,"remaining_time":12.09590115},
{"learn":[0.3734107469],"iteration":447,"passed_time":9.798208005,"remaining_time":12.07279201},
{"learn":[0.3733278911],"iteration":448,"passed_time":9.820416812,"remaining_time":12.05133555},
{"learn":[0.3732647389],"iteration":449,"passed_time":9.841547726,"remaining_time":12.02855833},
{"learn":[0.3732414478],"iteration":450,"passed_time":9.865134667,"remaining_time":12.00877812},
{"learn":[0.373123998],"iteration":451,"passed_time":9.888375611,"remaining_time":11.98856158},
{"learn":[0.3730028825],"iteration":452,"passed_time":9.911350325,"remaining_time":11.96801022},
{"learn":[0.3729466978],"iteration":453,"passed_time":9.9326898,"remaining_time":11.94548157},
{"learn":[0.3727815821],"iteration":454,"passed_time":9.954138569,"remaining_time":11.92308906},
{"learn":[0.3725948327],"iteration":455,"passed_time":9.976898405,"remaining_time":11.90226476},
{"learn":[0.3724395449],"iteration":456,"passed_time":9.999616647,"remaining_time":11.88138258},
{"learn":[0.3722550702],"iteration":457,"passed_time":10.02492757,"remaining_time":11.86356058},
{"learn":[0.372250233],"iteration":458,"passed_time":10.04635233,"remaining_time":11.84112551},
{"learn":[0.3721735693],"iteration":459,"passed_time":10.06861567,"remaining_time":11.81967927},
{"learn":[0.3720411547],"iteration":460,"passed_time":10.08961829,"remaining_time":11.79675544},
{"learn":[0.3719628787],"iteration":461,"passed_time":10.11151465,"remaining_time":11.77488069},
{"learn":[0.3719025324],"iteration":462,"passed_time":10.1335337,"remaining_time":11.75314816},
{"learn":[0.3718793323],"iteration":463,"passed_time":10.15571339,"remaining_time":11.73159995},
{"learn":[0.3718278691],"iteration":464,"passed_time":10.17824156,"remaining_time":11.71044996},
{"learn":[0.3718092371],"iteration":465,"passed_time":10.20407467,"remaining_time":11.69308127},
{"learn":[0.3717300093],"iteration":466,"passed_time":10.23394036,"remaining_time":11.68027883},
{"learn":[0.3715397147],"iteration":467,"passed_time":10.25860807,"remaining_time":11.66149464},
{"learn":[0.3714835858],"iteration":468,"passed_time":10.27964708,"remaining_time":11.63857697},
{"learn":[0.3712691236],"iteration":469,"passed_time":10.30153343,"remaining_time":11.6166228},
{"learn":[0.371173024],"iteration":470,"passed_time":10.3245406,"remaining_time":11.59592777},
{"learn":[0.37109895],"iteration":471,"passed_time":10.34889395,"remaining_time":11.57672882},
{"learn":[0.3710596759],"iteration":472,"passed_time":10.37032487,"remaining_time":11.55425202},
{"learn":[0.371059664],"iteration":473,"passed_time":10.37804888,"remaining_time":11.51656901},
{"learn":[0.3710303448],"iteration":474,"passed_time":10.40061377,"remaining_time":11.49541522},
{"learn":[0.3709813947],"iteration":475,"passed_time":10.42599598,"remaining_time":11.47735692},
{"learn":[0.3709130805],"iteration":476,"passed_time":10.44916037,"remaining_time":11.45683621},
{"learn":[0.3708549839],"iteration":477,"passed_time":10.47081176,"remaining_time":11.43465217},
{"learn":[0.3707544565],"iteration":478,"passed_time":10.49208448,"remaining_time":11.41205848},
{"learn":[0.3705986802],"iteration":479,"passed_time":10.51443254,"remaining_time":11.39063526},
{"learn":[0.3705818691],"iteration":480,"passed_time":10.52943642,"remaining_time":11.36128379},
{"learn":[0.3705032154],"iteration":481,"passed_time":10.58592149,"remaining_time":11.37657123},
{"learn":[0.370444293],"iteration":482,"passed_time":10.63458538,"remaining_time":11.38318974},
{"learn":[0.3703292583],"iteration":483,"passed_time":10.68052677,"remaining_time":11.3866773},
{"learn":[0.370081625],"iteration":484,"passed_time":10.72715779,"remaining_time":11.39069332},
{"learn":[0.3700618726],"iteration":485,"passed_time":10.79345023,"remaining_time":11.4152951},
{"learn":[0.3699563447],"iteration":486,"passed_time":10.8211982,"remaining_time":11.39892131},
{"learn":[0.3697568404],"iteration":487,"passed_time":10.84511637,"remaining_time":11.37848275},
{"learn":[0.3696933076],"iteration":488,"passed_time":10.86631284,"remaining_time":11.35518581},
{"learn":[0.3695823109],"iteration":489,"passed_time":10.88771484,"remaining_time":11.33211137},
{"learn":[0.3694872493],"iteration":490,"passed_time":10.90841349,"remaining_time":11.3083146},
{"learn":[0.3693292263],"iteration":491,"passed_time":10.93106035,"remaining_time":11.28654198},
{"learn":[0.3691862269],"iteration":492,"passed_time":10.95217652,"remaining_time":11.26319168},
{"learn":[0.3691513416],"iteration":493,"passed_time":10.96995482,"remaining_time":11.23643146},
{"learn":[0.3690928017],"iteration":494,"passed_time":10.99133454,"remaining_time":11.2133817},
{"learn":[0.3689868699],"iteration":495,"passed_time":11.01308262,"remaining_time":11.19071299},
{"learn":[0.368913626],"iteration":496,"passed_time":11.03649873,"remaining_time":11.16973614},
{"learn":[0.3688751667],"iteration":497,"passed_time":11.05773894,"remaining_time":11.14655612},
{"learn":[0.3686475567],"iteration":498,"passed_time":11.07998128,"remaining_time":11.12439002},
{"learn":[0.3686371393],"iteration":499,"passed_time":11.10491853,"remaining_time":11.10491853},
{"learn":[0.3685321008],"iteration":500,"passed_time":11.12702699,"remaining_time":11.08260772},
{"learn":[0.3684904754],"iteration":501,"passed_time":11.15072677,"remaining_time":11.06187635},
{"learn":[0.3684042788],"iteration":502,"passed_time":11.17184721,"remaining_time":11.03858462},
{"learn":[0.3681834102],"iteration":503,"passed_time":11.19434045,"remaining_time":11.01665251},
{"learn":[0.3679967159],"iteration":504,"passed_time":11.21690022,"remaining_time":10.99478338},
{"learn":[0.3679764092],"iteration":505,"passed_time":11.24242229,"remaining_time":10.97580358},
{"learn":[0.3679532239],"iteration":506,"passed_time":11.27035896,"remaining_time":10.95914589},
{"learn":[0.3678493674],"iteration":507,"passed_time":11.29421157,"remaining_time":10.93848837},
{"learn":[0.3677375261],"iteration":508,"passed_time":11.31695354,"remaining_time":10.91674693},
{"learn":[0.3676454451],"iteration":509,"passed_time":11.33930349,"remaining_time":10.89462492},
{"learn":[0.3673452315],"iteration":510,"passed_time":11.3614614,"remaining_time":10.87231825},
{"learn":[0.3671371289],"iteration":511,"passed_time":11.38614421,"remaining_time":10.8524187},
{"learn":[0.3670230371],"iteration":512,"passed_time":11.40801484,"remaining_time":10.82983085},
{"learn":[0.3669073247],"iteration":513,"passed_time":11.4313018,"remaining_time":10.80858497},
{"learn":[0.3668655527],"iteration":514,"passed_time":11.46113074,"remaining_time":10.79349205},
{"learn":[0.3668249554],"iteration":515,"passed_time":11.48739855,"remaining_time":10.77500174},
{"learn":[0.3667489408],"iteration":516,"passed_time":11.50949592,"remaining_time":10.75258517},
{"learn":[0.3667176235],"iteration":517,"passed_time":11.53037845,"remaining_time":10.72903941},
{"learn":[0.3666468683],"iteration":518,"passed_time":11.55189982,"remaining_time":10.70609598},
{"learn":[0.3665533827],"iteration":519,"passed_time":11.57508475,"remaining_time":10.68469362},
{"learn":[0.3665148152],"iteration":520,"passed_time":11.59590458,"remaining_time":10.66110997},
{"learn":[0.3663358565],"iteration":521,"passed_time":11.61702243,"remaining_time":10.63780981},
{"learn":[0.3661895597],"iteration":522,"passed_time":11.64054876,"remaining_time":10.61671465},
{"learn":[0.3661466315],"iteration":523,"passed_time":11.6616281,"remaining_time":10.59338736},
{"learn":[0.3658934051],"iteration":524,"passed_time":11.68433373,"remaining_time":10.57154004},
{"learn":[0.3657362782],"iteration":525,"passed_time":11.70609207,"remaining_time":10.54883582},
{"learn":[0.3656329792],"iteration":526,"passed_time":11.73008769,"remaining_time":10.52814322},
{"learn":[0.3655493455],"iteration":527,"passed_time":11.75278905,"remaining_time":10.50628112},
{"learn":[0.3653972438],"iteration":528,"passed_time":11.77599322,"remaining_time":10.48486353},
{"learn":[0.3653473539],"iteration":529,"passed_time":11.798532,"remaining_time":10.46284913},
{"learn":[0.3652965426],"iteration":530,"passed_time":11.81932735,"remaining_time":10.43929289},
{"learn":[0.3652267921],"iteration":531,"passed_time":11.84169177,"remaining_time":10.41712734},
{"learn":[0.3650476286],"iteration":532,"passed_time":11.86167774,"remaining_time":10.39287712},
{"learn":[0.36481827],"iteration":533,"passed_time":11.88501316,"remaining_time":10.37156579},
{"learn":[0.3647223604],"iteration":534,"passed_time":11.90725657,"remaining_time":10.34929777},
{"learn":[0.3646785748],"iteration":535,"passed_time":11.94888385,"remaining_time":10.3438099},
{"learn":[0.3646012715],"iteration":536,"passed_time":11.96925225,"remaining_time":10.31985809},
{"learn":[0.3644823292],"iteration":537,"passed_time":11.99146686,"remaining_time":10.297505},
{"learn":[0.3642882609],"iteration":538,"passed_time":12.01602283,"remaining_time":10.27715496},
{"learn":[0.3642189173],"iteration":539,"passed_time":12.04143919,"remaining_time":10.25752228},
{"learn":[0.3641570367],"iteration":540,"passed_time":12.06392048,"remaining_time":10.235378},
{"learn":[0.3640665013],"iteration":541,"passed_time":12.08585016,"remaining_time":10.21276638},
{"learn":[0.3639827506],"iteration":542,"passed_time":12.10869185,"remaining_time":10.19092482},
{"learn":[0.36395746],"iteration":543,"passed_time":12.13150787,"remaining_time":10.16905807},
{"learn":[0.3638543871],"iteration":544,"passed_time":12.15281393,"remaining_time":10.14592723},
{"learn":[0.3637661091],"iteration":545,"passed_time":12.17624155,"remaining_time":10.12456715},
{"learn":[0.3635834698],"iteration":546,"passed_time":12.19922825,"remaining_time":10.10283437},
{"learn":[0.3635269128],"iteration":547,"passed_time":12.22169564,"remaining_time":10.08066866},
{"learn":[0.3633090865],"iteration":548,"passed_time":12.24338093,"remaining_time":10.05785938},
{"learn":[0.3632406607],"iteration":549,"passed_time":12.26503071,"remaining_time":10.03502513},
{"learn":[0.3630290848],"iteration":550,"passed_time":12.28857345,"remaining_time":10.01373771},
{"learn":[0.3628339257],"iteration":551,"passed_time":12.32788515,"remaining_time":10.00524012},
{"learn":[0.3627611032],"iteration":552,"passed_time":12.34936517,"remaining_time":9.982217413},
{"learn":[0.3626906062],"iteration":553,"passed_time":12.37232383,"remaining_time":9.960390661},
{"learn":[0.362452386],"iteration":554,"passed_time":12.39590637,"remaining_time":9.939060061},
{"learn":[0.3623451894],"iteration":555,"passed_time":12.41950347,"remaining_time":9.91773299},
{"learn":[0.3622513754],"iteration":556,"passed_time":12.44228167,"remaining_time":9.895746459},
{"learn":[0.3621419719],"iteration":557,"passed_time":12.46357609,"remaining_time":9.872581778},
{"learn":[0.3620456768],"iteration":558,"passed_time":12.4861234,"remaining_time":9.850412199},
{"learn":[0.3618719799],"iteration":559,"passed_time":12.50811997,"remaining_time":9.827808546},
{"learn":[0.3616947253],"iteration":560,"passed_time":12.53007938,"remaining_time":9.805177983},
{"learn":[0.3615882136],"iteration":561,"passed_time":12.55061828,"remaining_time":9.781442715},
{"learn":[0.3615453098],"iteration":562,"passed_time":12.57419776,"remaining_time":9.760078902},
{"learn":[0.3615322263],"iteration":563,"passed_time":12.5960144,"remaining_time":9.737344468},
{"learn":[0.3614459404],"iteration":564,"passed_time":12.61850721,"remaining_time":9.715133871},
{"learn":[0.3613781259],"iteration":565,"passed_time":12.64092791,"remaining_time":9.692866983},
{"learn":[0.36132463],"iteration":566,"passed_time":12.66437233,"remaining_time":9.671381335},
{"learn":[0.3612405388],"iteration":567,"passed_time":12.68699153,"remaining_time":9.649261166},
{"learn":[0.3611256366],"iteration":568,"passed_time":12.70840037,"remaining_time":9.626222422},
{"learn":[0.3610083523],"iteration":569,"passed_time":12.72988219,"remaining_time":9.603244458},
{"learn":[0.3609483633],"iteration":570,"passed_time":12.75383318,"remaining_time":9.582126858},
{"learn":[0.3608749711],"iteration":571,"passed_time":12.77490711,"remaining_time":9.558846581},
{"learn":[0.3608470599],"iteration":572,"passed_time":12.79630775,"remaining_time":9.535817471},
{"learn":[0.36069453],"iteration":573,"passed_time":12.81786945,"remaining_time":9.512913561},
{"learn":[0.3605336416],"iteration":574,"passed_time":12.84246206,"remaining_time":9.492254568},
{"learn":[0.360464593],"iteration":575,"passed_time":12.86488689,"remaining_time":9.469986182},
{"learn":[0.3604098536],"iteration":576,"passed_time":12.88651016,"remaining_time":9.447129633},
{"learn":[0.3604012037],"iteration":577,"passed_time":12.90850791,"remaining_time":9.424550755},
{"learn":[0.3602839948],"iteration":578,"passed_time":12.9315339,"remaining_time":9.402721543},
{"learn":[0.3601337856],"iteration":579,"passed_time":12.95484448,"remaining_time":9.381094277},
{"learn":[0.3600088686],"iteration":580,"passed_time":12.9790909,"remaining_time":9.36013612},
{"learn":[0.359889255],"iteration":581,"passed_time":13.00330348,"remaining_time":9.339142364},
{"learn":[0.3598022107],"iteration":582,"passed_time":13.02595068,"remaining_time":9.317017899},
{"learn":[0.3597598934],"iteration":583,"passed_time":13.04968541,"remaining_time":9.295666318},
{"learn":[0.3596708998],"iteration":584,"passed_time":13.0787755,"remaining_time":9.278105695},
{"learn":[0.3595598256],"iteration":585,"passed_time":13.10288162,"remaining_time":9.256984626},
{"learn":[0.3594699683],"iteration":586,"passed_time":13.12496329,"remaining_time":9.234429024},
{"learn":[0.3594206821],"iteration":587,"passed_time":13.14623351,"remaining_time":9.211306473},
{"learn":[0.359347918],"iteration":588,"passed_time":13.1689364,"remaining_time":9.189189917},
{"learn":[0.3593223267],"iteration":589,"passed_time":13.19127474,"remaining_time":9.166818041},
{"learn":[0.3592391856],"iteration":590,"passed_time":13.21412407,"remaining_time":9.144799905},
{"learn":[0.3590938133],"iteration":591,"passed_time":13.23662965,"remaining_time":9.122542054},
{"learn":[0.3590468961],"iteration":592,"passed_time":13.26017087,"remaining_time":9.100994169},
{"learn":[0.3589716608],"iteration":593,"passed_time":13.28370224,"remaining_time":9.079432842},
{"learn":[0.358777585],"iteration":594,"passed_time":13.30544405,"remaining_time":9.056646793},
{"learn":[0.3587074519],"iteration":595,"passed_time":13.3273904,"remaining_time":9.034002889},
{"learn":[0.3586034866],"iteration":596,"passed_time":13.35061931,"remaining_time":9.012227108},
{"learn":[0.3584081665],"iteration":597,"passed_time":13.37148242,"remaining_time":8.988856077},
{"learn":[0.3582700551],"iteration":598,"passed_time":13.39631428,"remaining_time":8.968150291},
{"learn":[0.3582020722],"iteration":599,"passed_time":13.42031739,"remaining_time":8.946878261},
{"learn":[0.3580714499],"iteration":600,"passed_time":13.44120923,"remaining_time":8.923531583},
{"learn":[0.3579840678],"iteration":601,"passed_time":13.46178959,"remaining_time":8.89998714},
{"learn":[0.3579150798],"iteration":602,"passed_time":13.48275184,"remaining_time":8.876703945},
{"learn":[0.3578540206],"iteration":603,"passed_time":13.50608928,"remaining_time":8.854985689},
{"learn":[0.3576981387],"iteration":604,"passed_time":13.52863916,"remaining_time":8.832747879},
{"learn":[0.3575512115],"iteration":605,"passed_time":13.54930195,"remaining_time":8.809282125},
{"learn":[0.3573724509],"iteration":606,"passed_time":13.57192564,"remaining_time":8.787095184},
{"learn":[0.357288171],"iteration":607,"passed_time":13.59375737,"remaining_time":8.7643962},
{"learn":[0.357198322],"iteration":608,"passed_time":13.61549312,"remaining_time":8.741638437},
{"learn":[0.3570810175],"iteration":609,"passed_time":13.63698944,"remaining_time":8.718730956},
{"learn":[0.3569150071],"iteration":610,"passed_time":13.65996678,"remaining_time":8.696770991},
{"learn":[0.3568197227],"iteration":611,"passed_time":13.68402025,"remaining_time":8.675489961},
{"learn":[0.3566746128],"iteration":612,"passed_time":13.70839592,"remaining_time":8.654403296},
{"learn":[0.3564982535],"iteration":613,"passed_time":13.72970059,"remaining_time":8.631375287},
{"learn":[0.3564171073],"iteration":614,"passed_time":13.75375528,"remaining_time":8.610074443},
{"learn":[0.3562981445],"iteration":615,"passed_time":13.77507169,"remaining_time":8.587057677},
{"learn":[0.3562873647],"iteration":616,"passed_time":13.79878272,"remaining_time":8.565532869},
{"learn":[0.3562701279],"iteration":617,"passed_time":13.82209217,"remaining_time":8.543752768},
{"learn":[0.3562654119],"iteration":618,"passed_time":13.84433484,"remaining_time":8.521311103},
{"learn":[0.3561332136],"iteration":619,"passed_time":13.86502064,"remaining_time":8.497915878},
{"learn":[0.3560514023],"iteration":620,"passed_time":13.88645807,"remaining_time":8.4749881},
{"learn":[0.3559806244],"iteration":621,"passed_time":13.9094268,"remaining_time":8.452995707},
{"learn":[0.3559412926],"iteration":622,"passed_time":13.93244522,"remaining_time":8.431030251},
{"learn":[0.3558804816],"iteration":623,"passed_time":13.95467663,"remaining_time":8.408587201},
{"learn":[0.3557980794],"iteration":624,"passed_time":13.97827304,"remaining_time":8.386963826},
{"learn":[0.3556884057],"iteration":625,"passed_time":13.99997646,"remaining_time":8.364203188},
{"learn":[0.3554317485],"iteration":626,"passed_time":14.0214831,"remaining_time":8.34132886},
{"learn":[0.3553585441],"iteration":627,"passed_time":14.04320713,"remaining_time":8.318587664},
{"learn":[0.355314557],"iteration":628,"passed_time":14.06657875,"remaining_time":8.296821487},
{"learn":[0.3552380138],"iteration":629,"passed_time":14.08838295,"remaining_time":8.274129667},
{"learn":[0.3551075157],"iteration":630,"passed_time":14.11260022,"remaining_time":8.252851795},
{"learn":[0.3550304571],"iteration":631,"passed_time":14.13429682,"remaining_time":8.23009688},
{"learn":[0.3549816415],"iteration":632,"passed_time":14.15543722,"remaining_time":8.207022841},
{"learn":[0.3548952804],"iteration":633,"passed_time":14.17842728,"remaining_time":8.185022687},
{"learn":[0.3548597207],"iteration":634,"passed_time":14.20147778,"remaining_time":8.163054156},
{"learn":[0.3548290256],"iteration":635,"passed_time":14.22596318,"remaining_time":8.141903455},
{"learn":[0.3547639095],"iteration":636,"passed_time":14.24879927,"remaining_time":8.11980241},
{"learn":[0.3546812103],"iteration":637,"passed_time":14.27522846,"remaining_time":8.099737779},
{"learn":[0.35467491],"iteration":638,"passed_time":14.30511813,"remaining_time":8.081608208},
{"learn":[0.3545276473],"iteration":639,"passed_time":14.32734622,"remaining_time":8.059132249},
{"learn":[0.3543758765],"iteration":640,"passed_time":14.3517739,"remaining_time":8.037888968},
{"learn":[0.3542742789],"iteration":641,"passed_time":14.37501226,"remaining_time":8.015972571},
{"learn":[0.3542306848],"iteration":642,"passed_time":14.39636149,"remaining_time":7.993003192},
{"learn":[0.3541840025],"iteration":643,"passed_time":14.41868722,"remaining_time":7.970578648},
{"learn":[0.3541197722],"iteration":644,"passed_time":14.43957458,"remaining_time":7.947362753},
{"learn":[0.3540493057],"iteration":645,"passed_time":14.46435324,"remaining_time":7.926286448},
{"learn":[0.3540003639],"iteration":646,"passed_time":14.48686634,"remaining_time":7.903962624},
{"learn":[0.3538557259],"iteration":647,"passed_time":14.50705647,"remaining_time":7.880376356},
{"learn":[0.3537527176],"iteration":648,"passed_time":14.53018683,"remaining_time":7.858390719},
{"learn":[0.3537440971],"iteration":649,"passed_time":14.55046361,"remaining_time":7.834865022},
{"learn":[0.3536320847],"iteration":650,"passed_time":14.57221373,"remaining_time":7.812139155},
{"learn":[0.3535870562],"iteration":651,"passed_time":14.59557364,"remaining_time":7.7902755},
{"learn":[0.3535628036],"iteration":652,"passed_time":14.61709485,"remaining_time":7.767430187},
{"learn":[0.3535170767],"iteration":653,"passed_time":14.64030396,"remaining_time":7.745481913},
{"learn":[0.3534966262],"iteration":654,"passed_time":14.66416403,"remaining_time":7.723872655},
{"learn":[0.3533774637],"iteration":655,"passed_time":14.68403728,"remaining_time":7.700165891},
{"learn":[0.353212221],"iteration":656,"passed_time":14.70689229,"remaining_time":7.678027483},
{"learn":[0.3531985002],"iteration":657,"passed_time":14.72941071,"remaining_time":7.655711947},
{"learn":[0.3530714101],"iteration":658,"passed_time":14.75188313,"remaining_time":7.633371998},
{"learn":[0.3530265614],"iteration":659,"passed_time":14.77434899,"remaining_time":7.611028268},
{"learn":[0.3529227978],"iteration":660,"passed_time":14.79465193,"remaining_time":7.587574892},
{"learn":[0.3528764634],"iteration":661,"passed_time":14.81617512,"remaining_time":7.564754066},
{"learn":[0.3528455242],"iteration":662,"passed_time":14.8360717,"remaining_time":7.541110351},
{"learn":[0.3527685288],"iteration":663,"passed_time":14.86231977,"remaining_time":7.520691933},
{"learn":[0.3527335902],"iteration":664,"passed_time":14.88817947,"remaining_time":7.500060337},
{"learn":[0.3526009242],"iteration":665,"passed_time":14.9097319,"remaining_time":7.477252935},
{"learn":[0.352571381],"iteration":666,"passed_time":14.93265069,"remaining_time":7.455131453},
{"learn":[0.3523731058],"iteration":667,"passed_time":14.95261172,"remaining_time":7.431537563},
{"learn":[0.3523021258],"iteration":668,"passed_time":14.97741809,"remaining_time":7.410351849},
{"learn":[0.3520820374],"iteration":669,"passed_time":15.00130629,"remaining_time":7.388703099},
{"learn":[0.3520608],"iteration":670,"passed_time":15.0249716,"remaining_time":7.366938385},
{"learn":[0.3519345886],"iteration":671,"passed_time":15.04764865,"remaining_time":7.34468565},
{"learn":[0.351884814],"iteration":672,"passed_time":15.06887758,"remaining_time":7.321728034},
{"learn":[0.35177006],"iteration":673,"passed_time":15.09147478,"remaining_time":7.299437358},
{"learn":[0.3516626359],"iteration":674,"passed_time":15.11233585,"remaining_time":7.276309852},
{"learn":[0.3516206191],"iteration":675,"passed_time":15.13272164,"remaining_time":7.25296126},
{"learn":[0.3515654673],"iteration":676,"passed_time":15.15332167,"remaining_time":7.229723631},
{"learn":[0.3514670794],"iteration":677,"passed_time":15.17524245,"remaining_time":7.207121046},
{"learn":[0.3513957798],"iteration":678,"passed_time":15.19837837,"remaining_time":7.185094931},
{"learn":[0.3512858589],"iteration":679,"passed_time":15.22077116,"remaining_time":7.162715838},
{"learn":[0.3511851272],"iteration":680,"passed_time":15.24141456,"remaining_time":7.139517244},
{"learn":[0.3510901914],"iteration":681,"passed_time":15.264625,"remaining_time":7.117523093},
{"learn":[0.3509906313],"iteration":682,"passed_time":15.28787408,"remaining_time":7.095543315},
{"learn":[0.3509460584],"iteration":683,"passed_time":15.31426124,"remaining_time":7.07500958},
{"learn":[0.3509377964],"iteration":684,"passed_time":15.33755959,"remaining_time":7.053038353},
{"learn":[0.3508615007],"iteration":685,"passed_time":15.3595486,"remaining_time":7.030463935},
{"learn":[0.3507485683],"iteration":686,"passed_time":15.3824762,"remaining_time":7.008318852},
{"learn":[0.3506136111],"iteration":687,"passed_time":15.40545052,"remaining_time":6.986192678},
{"learn":[0.3504906385],"iteration":688,"passed_time":15.42836936,"remaining_time":6.964039001},
{"learn":[0.3504521154],"iteration":689,"passed_time":15.44941141,"remaining_time":6.941039911},
{"learn":[0.3503850258],"iteration":690,"passed_time":15.47080075,"remaining_time":6.918201783},
{"learn":[0.3503214247],"iteration":691,"passed_time":15.49356482,"remaining_time":6.895979719},
{"learn":[0.3501876981],"iteration":692,"passed_time":15.51495189,"remaining_time":6.873146077},
{"learn":[0.3500919001],"iteration":693,"passed_time":15.53542003,"remaining_time":6.849911427},
{"learn":[0.3500348351],"iteration":694,"passed_time":15.55656075,"remaining_time":6.826979899},
{"learn":[0.349990636],"iteration":695,"passed_time":15.57771193,"remaining_time":6.804058086},
{"learn":[0.3499771128],"iteration":696,"passed_time":15.59911125,"remaining_time":6.781249224},
{"learn":[0.3499289219],"iteration":697,"passed_time":15.62272366,"remaining_time":6.759401926},
{"learn":[0.3499152323],"iteration":698,"passed_time":15.64296414,"remaining_time":6.736097579},
{"learn":[0.3498792288],"iteration":699,"passed_time":15.66596709,"remaining_time":6.713985897},
{"learn":[0.3498111302],"iteration":700,"passed_time":15.69115124,"remaining_time":6.692802026},
{"learn":[0.3497383892],"iteration":701,"passed_time":15.71511267,"remaining_time":6.671087715},
{"learn":[0.3496724328],"iteration":702,"passed_time":15.73841245,"remaining_time":6.649087479},
{"learn":[0.3496297422],"iteration":703,"passed_time":15.76157871,"remaining_time":6.62702741},
{"learn":[0.3495768593],"iteration":704,"passed_time":15.78244151,"remaining_time":6.604000346},
{"learn":[0.3495642231],"iteration":705,"passed_time":15.80549536,"remaining_time":6.581891837},
{"learn":[0.3495274536],"iteration":706,"passed_time":15.83061854,"remaining_time":6.560638234},
{"learn":[0.3494737844],"iteration":707,"passed_time":15.85276187,"remaining_time":6.538144726},
{"learn":[0.3493277707],"iteration":708,"passed_time":15.87446188,"remaining_time":6.515470251},
{"learn":[0.3492921457],"iteration":709,"passed_time":15.90090161,"remaining_time":6.494734459},
{"learn":[0.3491733162],"iteration":710,"passed_time":15.92701558,"remaining_time":6.473850214},
{"learn":[0.349080963],"iteration":711,"passed_time":15.95293857,"remaining_time":6.452874029},
{"learn":[0.3489971875],"iteration":712,"passed_time":15.97420243,"remaining_time":6.43000855},
{"learn":[0.3489083476],"iteration":713,"passed_time":16.00887349,"remaining_time":6.412517954},
{"learn":[0.3488457787],"iteration":714,"passed_time":16.0323808,"remaining_time":6.390529409},
{"learn":[0.3488000526],"iteration":715,"passed_time":16.05657015,"remaining_time":6.368807156},
{"learn":[0.3487157973],"iteration":716,"passed_time":16.08103976,"remaining_time":6.347188638},
{"learn":[0.3486503589],"iteration":717,"passed_time":16.10251575,"remaining_time":6.324386409},
{"learn":[0.348527236],"iteration":718,"passed_time":16.13534032,"remaining_time":6.306023131},
{"learn":[0.3483937199],"iteration":719,"passed_time":16.15723637,"remaining_time":6.2833697},
{"learn":[0.3481920143],"iteration":720,"passed_time":16.18021356,"remaining_time":6.261136733},
{"learn":[0.3481339286],"iteration":721,"passed_time":16.20310329,"remaining_time":6.238868024},
{"learn":[0.348110116],"iteration":722,"passed_time":16.22609867,"remaining_time":6.216638079},
{"learn":[0.3480213433],"iteration":723,"passed_time":16.2473474,"remaining_time":6.193740167},
{"learn":[0.3479751286],"iteration":724,"passed_time":16.26826145,"remaining_time":6.17071986},
{"learn":[0.3478566016],"iteration":725,"passed_time":16.29075264,"remaining_time":6.148300582},
{"learn":[0.347694587],"iteration":726,"passed_time":16.31450833,"remaining_time":6.126355948},
{"learn":[0.3475946105],"iteration":727,"passed_time":16.33806479,"remaining_time":6.104331901},
{"learn":[0.347543436],"iteration":728,"passed_time":16.36031317,"remaining_time":6.08181738},
{"learn":[0.347502882],"iteration":729,"passed_time":16.38380796,"remaining_time":6.059764587},
{"learn":[0.3474241936],"iteration":730,"passed_time":16.40728062,"remaining_time":6.037699708},
{"learn":[0.3473449888],"iteration":731,"passed_time":16.42846379,"remaining_time":6.014792754},
{"learn":[0.3471902802],"iteration":732,"passed_time":16.45071364,"remaining_time":5.992279047},
{"learn":[0.3471011183],"iteration":733,"passed_time":16.47287059,"remaining_time":5.969732395},
{"learn":[0.3470779428],"iteration":734,"passed_time":16.49557477,"remaining_time":5.9473841},
{"learn":[0.3469679065],"iteration":735,"passed_time":16.51736822,"remaining_time":5.924708167},
{"learn":[0.3469039577],"iteration":736,"passed_time":16.53791437,"remaining_time":5.901589526},
{"learn":[0.3468451403],"iteration":737,"passed_time":16.56100375,"remaining_time":5.879380735},
{"learn":[0.3466587746],"iteration":738,"passed_time":16.58201237,"remaining_time":5.85643468},
{"learn":[0.3466302084],"iteration":739,"passed_time":16.60558129,"remaining_time":5.834393427},
{"learn":[0.3465430019],"iteration":740,"passed_time":16.62772613,"remaining_time":5.811850295},
{"learn":[0.3464847478],"iteration":741,"passed_time":16.6489772,"remaining_time":5.788997464},
{"learn":[0.3464238231],"iteration":742,"passed_time":16.67349633,"remaining_time":5.767279351},
{"learn":[0.3462950205],"iteration":743,"passed_time":16.69664925,"remaining_time":5.745083611},
{"learn":[0.346238337],"iteration":744,"passed_time":16.72134706,"remaining_time":5.723414094},
{"learn":[0.3461786659],"iteration":745,"passed_time":16.7444304,"remaining_time":5.701186759},
{"learn":[0.3460743974],"iteration":746,"passed_time":16.76597367,"remaining_time":5.678435527},
{"learn":[0.3460566455],"iteration":747,"passed_time":16.78683031,"remaining_time":5.655456199},
{"learn":[0.3459597192],"iteration":748,"passed_time":16.80991796,"remaining_time":5.633230183},
{"learn":[0.3459053024],"iteration":749,"passed_time":16.83143633,"remaining_time":5.610478777},
{"learn":[0.3458662021],"iteration":750,"passed_time":16.85559821,"remaining_time":5.58860713},
{"learn":[0.3458161581],"iteration":751,"passed_time":16.8770521,"remaining_time":5.565836331},
{"learn":[0.3457613838],"iteration":752,"passed_time":16.89943828,"remaining_time":5.543374839},
{"learn":[0.3456008267],"iteration":753,"passed_time":16.92260093,"remaining_time":5.521166882},
{"learn":[0.3455458168],"iteration":754,"passed_time":16.94663672,"remaining_time":5.499239729},
{"learn":[0.3454518615],"iteration":755,"passed_time":16.96953879,"remaining_time":5.47694109},
{"learn":[0.3454288671],"iteration":756,"passed_time":16.99207271,"remaining_time":5.454522678},
{"learn":[0.3453439244],"iteration":757,"passed_time":17.01403289,"remaining_time":5.431920791},
{"learn":[0.3451314399],"iteration":758,"passed_time":17.03613864,"remaining_time":5.409366816},
{"learn":[0.3450985365],"iteration":759,"passed_time":17.05911748,"remaining_time":5.387089729},
{"learn":[0.3450527204],"iteration":760,"passed_time":17.08016102,"remaining_time":5.364203001},
{"learn":[0.3450081554],"iteration":761,"passed_time":17.10682353,"remaining_time":5.343076116},
{"learn":[0.3449669843],"iteration":762,"passed_time":17.13520891,"remaining_time":5.322469872},
{"learn":[0.3449387755],"iteration":763,"passed_time":17.15780479,"remaining_time":5.300054883},
{"learn":[0.3448600243],"iteration":764,"passed_time":17.17953427,"remaining_time":5.277373273},
{"learn":[0.3447996665],"iteration":765,"passed_time":17.20241945,"remaining_time":5.255047194},
{"learn":[0.3447753625],"iteration":766,"passed_time":17.2264875,"remaining_time":5.233078994},
{"learn":[0.3447228106],"iteration":767,"passed_time":17.25174914,"remaining_time":5.211465887},
{"learn":[0.3446532804],"iteration":768,"passed_time":17.27416079,"remaining_time":5.188987182},
{"learn":[0.3445904254],"iteration":769,"passed_time":17.29800542,"remaining_time":5.166936685},
{"learn":[0.3445532197],"iteration":770,"passed_time":17.32064377,"remaining_time":5.144523246},
{"learn":[0.3445059776],"iteration":771,"passed_time":17.34161846,"remaining_time":5.121617888},
{"learn":[0.3444306014],"iteration":772,"passed_time":17.36463869,"remaining_time":5.099318218},
{"learn":[0.3442928526],"iteration":773,"passed_time":17.38627421,"remaining_time":5.076612366},
{"learn":[0.3441597077],"iteration":774,"passed_time":17.41311118,"remaining_time":5.055419374},
{"learn":[0.3441227929],"iteration":775,"passed_time":17.43980679,"remaining_time":5.034171033},
{"learn":[0.3439465287],"iteration":776,"passed_time":17.46426832,"remaining_time":5.012267485},
{"learn":[0.3438615661],"iteration":777,"passed_time":17.49155046,"remaining_time":4.991162213},
{"learn":[0.3437683728],"iteration":778,"passed_time":17.51766042,"remaining_time":4.969708539},
{"learn":[0.3436421814],"iteration":779,"passed_time":17.54457704,"remaining_time":4.948470446},
{"learn":[0.3436068553],"iteration":780,"passed_time":17.56856857,"remaining_time":4.92639759},
{"learn":[0.3435643912],"iteration":781,"passed_time":17.59017462,"remaining_time":4.903654818},
{"learn":[0.3435005878],"iteration":782,"passed_time":17.61258481,"remaining_time":4.881137809},
{"learn":[0.3434119016],"iteration":783,"passed_time":17.63366776,"remaining_time":4.858255404},
{"learn":[0.3432715014],"iteration":784,"passed_time":17.65844908,"remaining_time":4.836390513},
{"learn":[0.343241544],"iteration":785,"passed_time":17.67976521,"remaining_time":4.813574752},
{"learn":[0.3430991039],"iteration":786,"passed_time":17.7011393,"remaining_time":4.790778488},
{"learn":[0.3430587358],"iteration":787,"passed_time":17.72355373,"remaining_time":4.768265725},
{"learn":[0.3430061169],"iteration":788,"passed_time":17.74538731,"remaining_time":4.745597874},
{"learn":[0.3429418283],"iteration":789,"passed_time":17.76927652,"remaining_time":4.723478567},
{"learn":[0.3427935573],"iteration":790,"passed_time":17.79089427,"remaining_time":4.700754617},
{"learn":[0.3427456137],"iteration":791,"passed_time":17.81281223,"remaining_time":4.678112304},
{"learn":[0.3427195313],"iteration":792,"passed_time":17.83544332,"remaining_time":4.655657967},
{"learn":[0.3425333427],"iteration":793,"passed_time":17.85723624,"remaining_time":4.632985726},
{"learn":[0.342412934],"iteration":794,"passed_time":17.87988406,"remaining_time":4.610536141},
{"learn":[0.3424028075],"iteration":795,"passed_time":17.9023275,"remaining_time":4.588033681},
{"learn":[0.3423196592],"iteration":796,"passed_time":17.92273644,"remaining_time":4.565013171},
{"learn":[0.3422804786],"iteration":797,"passed_time":17.9458076,"remaining_time":4.542673102},
{"learn":[0.3420549367],"iteration":798,"passed_time":17.96665061,"remaining_time":4.519770678},
{"learn":[0.3420483619],"iteration":799,"passed_time":17.9904562,"remaining_time":4.49761405},
{"learn":[0.3420431209],"iteration":800,"passed_time":18.01436181,"remaining_time":4.475478152},
{"learn":[0.3420339558],"iteration":801,"passed_time":18.03551063,"remaining_time":4.452657238},
{"learn":[0.3419718888],"iteration":802,"passed_time":18.05896558,"remaining_time":4.43040625},
{"learn":[0.3419048116],"iteration":803,"passed_time":18.08215676,"remaining_time":4.408087966},
{"learn":[0.3417413609],"iteration":804,"passed_time":18.10259616,"remaining_time":4.385100932},
{"learn":[0.341716735],"iteration":805,"passed_time":18.12492962,"remaining_time":4.362576111},
{"learn":[0.3415911915],"iteration":806,"passed_time":18.14613261,"remaining_time":4.339781404},
{"learn":[0.3415815278],"iteration":807,"passed_time":18.16929896,"remaining_time":4.317457178},
{"learn":[0.3415254056],"iteration":808,"passed_time":18.19354219,"remaining_time":4.295385116},
{"learn":[0.3414292735],"iteration":809,"passed_time":18.21484139,"remaining_time":4.272617117},
{"learn":[0.3412880958],"iteration":810,"passed_time":18.23648853,"remaining_time":4.249933826},
{"learn":[0.3411792282],"iteration":811,"passed_time":18.25959951,"remaining_time":4.227592004},
{"learn":[0.3411592801],"iteration":812,"passed_time":18.28875155,"remaining_time":4.206637811},
{"learn":[0.3410784953],"iteration":813,"passed_time":18.3157486,"remaining_time":4.185171056},
{"learn":[0.3410305929],"iteration":814,"passed_time":18.33898308,"remaining_time":4.162836651},
{"learn":[0.3408994363],"iteration":815,"passed_time":18.3627266,"remaining_time":4.140614822},
{"learn":[0.3408598505],"iteration":816,"passed_time":18.38682314,"remaining_time":4.11846834},
{"learn":[0.3407546281],"iteration":817,"passed_time":18.41020538,"remaining_time":4.096158165},
{"learn":[0.3407308779],"iteration":818,"passed_time":18.43312084,"remaining_time":4.073742212},
{"learn":[0.3407150687],"iteration":819,"passed_time":18.45855131,"remaining_time":4.051877117},
{"learn":[0.3406522282],"iteration":820,"passed_time":18.48016565,"remaining_time":4.029171316},
{"learn":[0.3405748223],"iteration":821,"passed_time":18.50264612,"remaining_time":4.006655728},
{"learn":[0.3404356997],"iteration":822,"passed_time":18.5267497,"remaining_time":3.984489303},
{"learn":[0.3403274442],"iteration":823,"passed_time":18.54771032,"remaining_time":3.961646865},
{"learn":[0.3402509172],"iteration":824,"passed_time":18.56983654,"remaining_time":3.939056237},
{"learn":[0.3402296039],"iteration":825,"passed_time":18.59146744,"remaining_time":3.91636239},
{"learn":[0.3400840554],"iteration":826,"passed_time":18.61480562,"remaining_time":3.894028262},
{"learn":[0.340049446],"iteration":827,"passed_time":18.63654788,"remaining_time":3.871360189},
{"learn":[0.3400077713],"iteration":828,"passed_time":18.65921828,"remaining_time":3.848885797},
{"learn":[0.3399395559],"iteration":829,"passed_time":18.68172975,"remaining_time":3.826378382},
{"learn":[0.3398963159],"iteration":830,"passed_time":18.7030505,"remaining_time":3.803628802},
{"learn":[0.3398525345],"iteration":831,"passed_time":18.725412,"remaining_time":3.781092808},
{"learn":[0.3397059108],"iteration":832,"passed_time":18.74792807,"remaining_time":3.75858822},
{"learn":[0.3396712678],"iteration":833,"passed_time":18.76912849,"remaining_time":3.735821738},
{"learn":[0.3396478361],"iteration":834,"passed_time":18.79218199,"remaining_time":3.713425184},
{"learn":[0.3396030096],"iteration":835,"passed_time":18.81174749,"remaining_time":3.690342808},
{"learn":[0.339534235],"iteration":836,"passed_time":18.83378447,"remaining_time":3.667750142},
{"learn":[0.3394009057],"iteration":837,"passed_time":18.85823952,"remaining_time":3.645626255},
{"learn":[0.3392886531],"iteration":838,"passed_time":18.87962285,"remaining_time":3.622907365},
{"learn":[0.3392147488],"iteration":839,"passed_time":18.90119189,"remaining_time":3.600227026},
{"learn":[0.3392034519],"iteration":840,"passed_time":18.92288514,"remaining_time":3.577572815},
{"learn":[0.3391509978],"iteration":841,"passed_time":18.94750429,"remaining_time":3.555469927},
{"learn":[0.3391023704],"iteration":842,"passed_time":18.97050663,"remaining_time":3.533059953},
{"learn":[0.3390905257],"iteration":843,"passed_time":18.9941177,"remaining_time":3.510761092},
{"learn":[0.3390415623],"iteration":844,"passed_time":19.0159658,"remaining_time":3.488135739},
{"learn":[0.3389962146],"iteration":845,"passed_time":19.03708454,"remaining_time":3.465379455},
{"learn":[0.3389194535],"iteration":846,"passed_time":19.06009635,"remaining_time":3.442968998},
{"learn":[0.3388454699],"iteration":847,"passed_time":19.08251226,"remaining_time":3.420450311},
{"learn":[0.3388444258],"iteration":848,"passed_time":19.10591867,"remaining_time":3.398108033},
{"learn":[0.3388010981],"iteration":849,"passed_time":19.12680405,"remaining_time":3.375318363},
{"learn":[0.3387215584],"iteration":850,"passed_time":19.14920636,"remaining_time":3.352798764},
{"learn":[0.3386773961],"iteration":851,"passed_time":19.17120922,"remaining_time":3.330210052},
{"learn":[0.33860309],"iteration":852,"passed_time":19.1940461,"remaining_time":3.307766443},
{"learn":[0.3385394453],"iteration":853,"passed_time":19.21527804,"remaining_time":3.285047533},
{"learn":[0.3385139369],"iteration":854,"passed_time":19.23906719,"remaining_time":3.26276578},
{"learn":[0.3384279488],"iteration":855,"passed_time":19.26384705,"remaining_time":3.240647166},
{"learn":[0.3384005795],"iteration":856,"passed_time":19.28618464,"remaining_time":3.218114823},
{"learn":[0.3383784629],"iteration":857,"passed_time":19.30840957,"remaining_time":3.195564287},
{"learn":[0.3382676146],"iteration":858,"passed_time":19.33032547,"remaining_time":3.172963785},
{"learn":[0.3381637375],"iteration":859,"passed_time":19.35235736,"remaining_time":3.150383757},
{"learn":[0.3381537302],"iteration":860,"passed_time":19.37588987,"remaining_time":3.128047261},
{"learn":[0.3381118125],"iteration":861,"passed_time":19.40086465,"remaining_time":3.105938889},
{"learn":[0.3380844861],"iteration":862,"passed_time":19.42234552,"remaining_time":3.083269219},
{"learn":[0.338025707],"iteration":863,"passed_time":19.44471669,"remaining_time":3.060742442},
{"learn":[0.3379542884],"iteration":864,"passed_time":19.46571423,"remaining_time":3.038001643},
{"learn":[0.3379182297],"iteration":865,"passed_time":19.48785294,"remaining_time":3.015441448},
{"learn":[0.3378892861],"iteration":866,"passed_time":19.50909109,"remaining_time":2.992744078},
{"learn":[0.3377715457],"iteration":867,"passed_time":19.52943123,"remaining_time":2.969913506},
{"learn":[0.3376520222],"iteration":868,"passed_time":19.55238268,"remaining_time":2.947482315},
{"learn":[0.3375677296],"iteration":869,"passed_time":19.57295735,"remaining_time":2.924694777},
{"learn":[0.3374843613],"iteration":870,"passed_time":19.59645474,"remaining_time":2.902345191},
{"learn":[0.3373782423],"iteration":871,"passed_time":19.61686184,"remaining_time":2.879539353},
{"learn":[0.3372040864],"iteration":872,"passed_time":19.64060759,"remaining_time":2.8572247},
{"learn":[0.3371285382],"iteration":873,"passed_time":19.6641952,"remaining_time":2.834883976},
{"learn":[0.337044703],"iteration":874,"passed_time":19.6875224,"remaining_time":2.8125032},
{"learn":[0.3369606863],"iteration":875,"passed_time":19.71358542,"remaining_time":2.790507525},
{"learn":[0.3368578433],"iteration":876,"passed_time":19.73528929,"remaining_time":2.7678912},
{"learn":[0.3367271119],"iteration":877,"passed_time":19.75660025,"remaining_time":2.745222358},
{"learn":[0.3366852006],"iteration":878,"passed_time":19.77792088,"remaining_time":2.722557937},
{"learn":[0.3366643791],"iteration":879,"passed_time":19.80170824,"remaining_time":2.700232941},
{"learn":[0.3366411359],"iteration":880,"passed_time":19.82162111,"remaining_time":2.677381285},
{"learn":[0.3365873953],"iteration":881,"passed_time":19.8451023,"remaining_time":2.655013687},
{"learn":[0.3364333541],"iteration":882,"passed_time":19.87103696,"remaining_time":2.632968657},
{"learn":[0.3363477852],"iteration":883,"passed_time":19.89988088,"remaining_time":2.611296587},
{"learn":[0.3362675438],"iteration":884,"passed_time":19.92606464,"remaining_time":2.589262637},
{"learn":[0.336143856],"iteration":885,"passed_time":19.9465285,"remaining_time":2.566483351},
{"learn":[0.3360918646],"iteration":886,"passed_time":19.9701917,"remaining_time":2.544116868},
{"learn":[0.3360242062],"iteration":887,"passed_time":19.99205687,"remaining_time":2.521520686},
{"learn":[0.3359195657],"iteration":888,"passed_time":20.01541879,"remaining_time":2.499113032},
{"learn":[0.3358630109],"iteration":889,"passed_time":20.03966871,"remaining_time":2.476812987},
{"learn":[0.3357511564],"iteration":890,"passed_time":20.06177724,"remaining_time":2.454246598},
{"learn":[0.3356965958],"iteration":891,"passed_time":20.08412033,"remaining_time":2.431709637},
{"learn":[0.335577762],"iteration":892,"passed_time":20.10739065,"remaining_time":2.40928421},
{"learn":[0.3355404353],"iteration":893,"passed_time":20.12889406,"remaining_time":2.386647394},
{"learn":[0.3353984529],"iteration":894,"passed_time":20.15056211,"remaining_time":2.364032426},
{"learn":[0.3352915734],"iteration":895,"passed_time":20.17178985,"remaining_time":2.341368464},
{"learn":[0.3352061824],"iteration":896,"passed_time":20.19518471,"remaining_time":2.31895655},
{"learn":[0.3351741599],"iteration":897,"passed_time":20.21869634,"remaining_time":2.296555709},
{"learn":[0.3351542754],"iteration":898,"passed_time":20.24196262,"remaining_time":2.274124833},
{"learn":[0.3351126072],"iteration":899,"passed_time":20.26358998,"remaining_time":2.251509997},
{"learn":[0.335031682],"iteration":900,"passed_time":20.28668518,"remaining_time":2.229058638},
{"learn":[0.3349715917],"iteration":901,"passed_time":20.30820306,"remaining_time":2.206434479},
{"learn":[0.3348681135],"iteration":902,"passed_time":20.32957968,"remaining_time":2.183797596},
{"learn":[0.3348430617],"iteration":903,"passed_time":20.35279083,"remaining_time":2.161358318},
{"learn":[0.33471942],"iteration":904,"passed_time":20.37522662,"remaining_time":2.138835944},
{"learn":[0.3346929643],"iteration":905,"passed_time":20.39863182,"remaining_time":2.116414339},
{"learn":[0.3346244215],"iteration":906,"passed_time":20.41833279,"remaining_time":2.09361075},
{"learn":[0.3346176946],"iteration":907,"passed_time":20.44305979,"remaining_time":2.071323239},
{"learn":[0.3345925978],"iteration":908,"passed_time":20.46434225,"remaining_time":2.048685528},
{"learn":[0.334455331],"iteration":909,"passed_time":20.48581049,"remaining_time":2.02606917},
{"learn":[0.3343843107],"iteration":910,"passed_time":20.50836349,"remaining_time":2.003561307},
{"learn":[0.3342794003],"iteration":911,"passed_time":20.53174949,"remaining_time":1.981133722},
{"learn":[0.3341944283],"iteration":912,"passed_time":20.5556101,"remaining_time":1.958749265},
{"learn":[0.3340970726],"iteration":913,"passed_time":20.57783971,"remaining_time":1.936208113},
{"learn":[0.3340933104],"iteration":914,"passed_time":20.59941328,"remaining_time":1.913606698},
{"learn":[0.3340146947],"iteration":915,"passed_time":20.62153737,"remaining_time":1.891058012},
{"learn":[0.3338649537],"iteration":916,"passed_time":20.64530487,"remaining_time":1.868659002},
{"learn":[0.3337298609],"iteration":917,"passed_time":20.66723937,"remaining_time":1.846093277},
{"learn":[0.3336340409],"iteration":918,"passed_time":20.69001418,"remaining_time":1.823602991},
{"learn":[0.3335433824],"iteration":919,"passed_time":20.71327148,"remaining_time":1.801154042},
{"learn":[0.333494045],"iteration":920,"passed_time":20.73536025,"remaining_time":1.778603105},
{"learn":[0.3334553326],"iteration":921,"passed_time":20.76980769,"remaining_time":1.757098699},
{"learn":[0.3334145635],"iteration":922,"passed_time":20.79069664,"remaining_time":1.734435148},
{"learn":[0.3333515498],"iteration":923,"passed_time":20.81198049,"remaining_time":1.711807919},
{"learn":[0.3333180769],"iteration":924,"passed_time":20.83481249,"remaining_time":1.689309121},
{"learn":[0.3332829108],"iteration":925,"passed_time":20.85711953,"remaining_time":1.666767651},
{"learn":[0.3331541523],"iteration":926,"passed_time":20.87979343,"remaining_time":1.644255578},
{"learn":[0.3330821824],"iteration":927,"passed_time":20.90162784,"remaining_time":1.621678022},
{"learn":[0.3330590435],"iteration":928,"passed_time":20.92412049,"remaining_time":1.599152373},
{"learn":[0.3329379122],"iteration":929,"passed_time":20.94524776,"remaining_time":1.576524025},
{"learn":[0.3328723248],"iteration":930,"passed_time":20.96989934,"remaining_time":1.554160102},
{"learn":[0.3328020684],"iteration":931,"passed_time":20.99343348,"remaining_time":1.531709739},
{"learn":[0.3327193],"iteration":932,"passed_time":21.01493983,"remaining_time":1.509111435},
{"learn":[0.3326062285],"iteration":933,"passed_time":21.03855535,"remaining_time":1.486664511},
{"learn":[0.3325660358],"iteration":934,"passed_time":21.06802072,"remaining_time":1.464621761},
{"learn":[0.3325223805],"iteration":935,"passed_time":21.09400535,"remaining_time":1.442325152},
{"learn":[0.3324976588],"iteration":936,"passed_time":21.11603178,"remaining_time":1.419754538},
{"learn":[0.3323380073],"iteration":937,"passed_time":21.13687806,"remaining_time":1.397107078},
{"learn":[0.3322201423],"iteration":938,"passed_time":21.16077837,"remaining_time":1.374661853},
{"learn":[0.3321412604],"iteration":939,"passed_time":21.18453527,"remaining_time":1.352204379},
{"learn":[0.332078126],"iteration":940,"passed_time":21.20730015,"remaining_time":1.329681943},
{"learn":[0.3320703883],"iteration":941,"passed_time":21.22949098,"remaining_time":1.307123648},
{"learn":[0.332041331],"iteration":942,"passed_time":21.25259898,"remaining_time":1.284621571},
{"learn":[0.3319375347],"iteration":943,"passed_time":21.2755503,"remaining_time":1.262108916},
{"learn":[0.331815933],"iteration":944,"passed_time":21.29796143,"remaining_time":1.239563893},
{"learn":[0.3316489595],"iteration":945,"passed_time":21.31915555,"remaining_time":1.216949683},
{"learn":[0.3314701513],"iteration":946,"passed_time":21.34079183,"remaining_time":1.194363217},
{"learn":[0.3313350792],"iteration":947,"passed_time":21.36227288,"remaining_time":1.171770242},
{"learn":[0.3312614334],"iteration":948,"passed_time":21.38707455,"remaining_time":1.149358063},
{"learn":[0.3312286819],"iteration":949,"passed_time":21.40974203,"remaining_time":1.126828528},
{"learn":[0.3311904294],"iteration":950,"passed_time":21.43139844,"remaining_time":1.104246607},
{"learn":[0.3311876494],"iteration":951,"passed_time":21.45299083,"remaining_time":1.081663403},
{"learn":[0.3310750266],"iteration":952,"passed_time":21.47555249,"remaining_time":1.059130081},
{"learn":[0.3310206668],"iteration":953,"passed_time":21.49859293,"remaining_time":1.036619785},
{"learn":[0.3308778677],"iteration":954,"passed_time":21.52124439,"remaining_time":1.01409005},
{"learn":[0.3306990896],"iteration":955,"passed_time":21.54227916,"remaining_time":0.9914856518},
{"learn":[0.3306373775],"iteration":956,"passed_time":21.56434065,"remaining_time":0.9689306664},
{"learn":[0.330519121],"iteration":957,"passed_time":21.5864927,"remaining_time":0.9463806822},
{"learn":[0.330463448],"iteration":958,"passed_time":21.60845884,"remaining_time":0.9238235792},
{"learn":[0.3303026072],"iteration":959,"passed_time":21.63118125,"remaining_time":0.9012992188},
{"learn":[0.3302076323],"iteration":960,"passed_time":21.65500581,"remaining_time":0.8788191745},
{"learn":[0.3301837116],"iteration":961,"passed_time":21.67731949,"remaining_time":0.8562766535},
{"learn":[0.3300425376],"iteration":962,"passed_time":21.70090676,"remaining_time":0.833783541},
{"learn":[0.3299839329],"iteration":963,"passed_time":21.72156536,"remaining_time":0.8111787895},
{"learn":[0.3299613479],"iteration":964,"passed_time":21.74432426,"remaining_time":0.7886542476},
{"learn":[0.3299244202],"iteration":965,"passed_time":21.76563937,"remaining_time":0.7660784045},
{"learn":[0.3298921336],"iteration":966,"passed_time":21.78878138,"remaining_time":0.7435675133},
{"learn":[0.3297727199],"iteration":967,"passed_time":21.81080496,"remaining_time":0.7210183458},
{"learn":[0.3296389541],"iteration":968,"passed_time":21.83223588,"remaining_time":0.6984513027},
{"learn":[0.3295226026],"iteration":969,"passed_time":21.85494913,"remaining_time":0.6759262618},
{"learn":[0.3294783991],"iteration":970,"passed_time":21.87882223,"remaining_time":0.6534354735},
{"learn":[0.3294008213],"iteration":971,"passed_time":21.8996609,"remaining_time":0.6308544293},
{"learn":[0.3293664868],"iteration":972,"passed_time":21.92271977,"remaining_time":0.6083385753},
{"learn":[0.3293331271],"iteration":973,"passed_time":21.94397107,"remaining_time":0.585773355},
{"learn":[0.3291018509],"iteration":974,"passed_time":21.96555285,"remaining_time":0.5632193039},
{"learn":[0.3290705262],"iteration":975,"passed_time":21.98943106,"remaining_time":0.5407237147},
{"learn":[0.3290192025],"iteration":976,"passed_time":22.01126198,"remaining_time":0.5181770988},
{"learn":[0.328898948],"iteration":977,"passed_time":22.03384928,"remaining_time":0.4956489614},
{"learn":[0.3288688393],"iteration":978,"passed_time":22.05858817,"remaining_time":0.4731668556},
{"learn":[0.3288376079],"iteration":979,"passed_time":22.08004312,"remaining_time":0.4506131249},
{"learn":[0.3287790262],"iteration":980,"passed_time":22.10263588,"remaining_time":0.4280836715},
{"learn":[0.3287464441],"iteration":981,"passed_time":22.12581208,"remaining_time":0.4055647835},
{"learn":[0.3287242567],"iteration":982,"passed_time":22.14834301,"remaining_time":0.383033399},
{"learn":[0.3286931429],"iteration":983,"passed_time":22.17370431,"remaining_time":0.3605480376},
{"learn":[0.3286296659],"iteration":984,"passed_time":22.19562865,"remaining_time":0.3380044972},
{"learn":[0.3285070103],"iteration":985,"passed_time":22.21944523,"remaining_time":0.3154890803},
{"learn":[0.3284098004],"iteration":986,"passed_time":22.24360534,"remaining_time":0.2929755516},
{"learn":[0.3283759777],"iteration":987,"passed_time":22.26565291,"remaining_time":0.2704330313},
{"learn":[0.3283703759],"iteration":988,"passed_time":22.28720927,"remaining_time":0.2478860485},
{"learn":[0.3283486294],"iteration":989,"passed_time":22.30935755,"remaining_time":0.225347046},
{"learn":[0.3282414489],"iteration":990,"passed_time":22.32985958,"remaining_time":0.2027938811},
{"learn":[0.328236007],"iteration":991,"passed_time":22.35245292,"remaining_time":0.1802617171},
{"learn":[0.3281900372],"iteration":992,"passed_time":22.37514729,"remaining_time":0.157730142},
{"learn":[0.3281326425],"iteration":993,"passed_time":22.39817532,"remaining_time":0.1352002534},
{"learn":[0.328058808],"iteration":994,"passed_time":22.42060657,"remaining_time":0.1126663647},
{"learn":[0.3280237204],"iteration":995,"passed_time":22.44331044,"remaining_time":0.09013377686},
{"learn":[0.3279093123],"iteration":996,"passed_time":22.46657631,"remaining_time":0.06760253654},
{"learn":[0.3277912165],"iteration":997,"passed_time":22.48875296,"remaining_time":0.0450676412},
{"learn":[0.327766398],"iteration":998,"passed_time":22.51053427,"remaining_time":0.02253306733},
{"learn":[0.3277529062],"iteration":999,"passed_time":22.53172214,"remaining_time":0}
]}